Workbook

Sheet Dashboard
B1: 📊 DASHBOARD — Natural Mix
B3: 📅 Filtro de Mês: | E3: Setembro | G3: ⬅ Selecione o mês para atualizar
C6: 💸 | D6: Despesas | F6: 📊 | G6: Margem
D7: =SUMIF(Despesas_DB!C4:C99,$E$3,Despesas_DB!H4:H99) -> 1943 | G7: =IFERROR(D13/J10,0) -> 0.45281478
C9: 🛒 | D9: Pedidos | F9: 🎯 | G9: Ticket | J9: 💰 Faturamento
D10: =COUNTIF(Pedidos_DB!C4:C110,$E$3) -> 11 | G10: =IFERROR(J10/D10,0) -> 322.80909 | J10: =SUMIF(Pedidos_DB!C4:C110,$E$3,Pedidos_DB!G4:G110) -> 3550.9
C12: 📈 | D12: Lucro | F12: ✅ | G12: Concluídos
D13: =J10-D7 -> 1607.9 | G13: =SUMPRODUCT((Pedidos_DB!C4:C110=$E$3)*(LOWER(Pedidos_DB!H4:H110)="concluído")) -> 11
Q21: =C49 -> 0 | R21: =G49 -> 0
Q22: =C50 -> 0 | R22: =G50 -> 0
C64: Selecione o mês em D4 • Projeto de Extensão — Análise de Dados

Sheet Pedidos
B1: 🛒 CONTROLE DE PEDIDOS
B2: 📅 Filtro de Mês: | D2: Setembro | G2: ⬅ Selecione o mês para atualizar
B4: 💰 Faturamento | D4: 🛒 Pedidos | F4: ✅ Concluídos | H4: ⏳ Pendentes | J4: 🎯 Ticket Médio | K4: 🔄 Processo
B5: =SUMIF(Pedidos_DB!C4:C110,$D$2,Pedidos_DB!G4:G110) -> 3550.9 | D5: =COUNTIF(Pedidos_DB!C4:C110,$D$2) -> 11 | F5: =SUMPRODUCT((Pedidos_DB!C4:C110=$D$2)*(LOWER(Pedidos_DB!H4:H110)="concluído")) -> 11 | H5: =SUMPRODUCT((Pedidos_DB!C4:C110=$D$2)*(LOWER(Pedidos_DB!H4:H110)="pendente")) -> 0 | J5: =IFERROR(B5/D5,0) -> 322.80909 | K5: =SUMPRODUCT((Pedidos_DB!C4:C110=$D$2)*(LOWER(Pedidos_DB!H4:H110)="processo")) -> 0
B8: 📋 Pedidos do Mês Selecionado | J8: 🏪 Fat. por Salão
B9: Data | C9: Mês | D9: Cliente/Salão | E9: Produto | F9: Qtd | G9: Valor (R$) | H9: Status | J9: Salão | L9: Valor (R$)
B10: =IFERROR(IF(INDEX(Pedidos_DB!C:C,3+MATCH($D$2,Pedidos_DB!C4:C110,0)+0)<>$D$2,"",INDEX(Pedidos_DB!B:B,3+MATCH($D$2,Pedidos_DB!C4:C110,0)+0)),"") -> 2024-09-03 | C10: =IFERROR(IF(INDEX(Pedidos_DB!C:C,3+MATCH($D$2,Pedidos_DB!C4:C110,0)+0)<>$D$2,"",INDEX(Pedidos_DB!C:C,3+MATCH($D$2,Pedidos_DB!C4:C110,0)+0)),"") -> Setembro | D10: =IFERROR(IF(INDEX(Pedidos_DB!C:C,3+MATCH($D$2,Pedidos_DB!C4:C110,0)+0)<>$D$2,"",INDEX(Pedidos_DB!D:D,3+MATCH($D$2,Pedidos_DB!C4:C110,0)+0)),"") -> Salão Glamour | E10: =IFERROR(IF(INDEX(Pedidos_DB!C:C,3+MATCH($D$2,Pedidos_DB!C4:C110,0)+0)<>$D$2,"",INDEX(Pedidos_DB!E:E,3+MATCH($D$2,Pedidos_DB!C4:C110,0)+0)),"") -> Shampoo Antiqueda | F10: =IFERROR(IF(INDEX(Pedidos_DB!C:C,3+MATCH($D$2,Pedidos_DB!C4:C110,0)+0)<>$D$2,"",INDEX(Pedidos_DB!F:F,3+MATCH($D$2,Pedidos_DB!C4:C110,0)+0)),"") -> 15 | G10: =IFERROR(IF(INDEX(Pedidos_DB!C:C,3+MATCH($D$2,Pedidos_DB!C4:C110,0)+0)<>$D$2,"",INDEX(Pedidos_DB!G:G,3+MATCH($D$2,Pedidos_DB!C4:C110,0)+0)),"") -> 283.5 | H10: =IFERROR(IF(INDEX(Pedidos_DB!C:C,3+MATCH($D$2,Pedidos_DB!C4:C110,0)+0)<>$D$2,"",INDEX(Pedidos_DB!H:H,3+MATCH($D$2,Pedidos_DB!C4:C110,0)+0)),"") -> concluído | J10: Salão Beleza & Cia | L10: =SUMPRODUCT((Pedidos_DB!C4:C110=$D$2)*(Pedidos_DB!D4:D110=J10)*Pedidos_DB!G4:G110) -> 545
B11: =IFERROR(IF(INDEX(Pedidos_DB!C:C,3+MATCH($D$2,Pedidos_DB!C4:C110,0)+1)<>$D$2,"",INDEX(Pedidos_DB!B:B,3+MATCH($D$2,Pedidos_DB!C4:C110,0)+1)),"") -> 2024-09-05 | C11: =IFERROR(IF(INDEX(Pedidos_DB!C:C,3+MATCH($D$2,Pedidos_DB!C4:C110,0)+1)<>$D$2,"",INDEX(Pedidos_DB!C:C,3+MATCH($D$2,Pedidos_DB!C4:C110,0)+1)),"") -> Setembro | D11: =IFERROR(IF(INDEX(Pedidos_DB!C:C,3+MATCH($D$2,Pedidos_DB!C4:C110,0)+1)<>$D$2,"",INDEX(Pedidos_DB!D:D,3+MATCH($D$2,Pedidos_DB!C4:C110,0)+1)),"") -> Salão Cabelos de Ouro | E11: =IFERROR(IF(INDEX(Pedidos_DB!C:C,3+MATCH($D$2,Pedidos_DB!C4:C110,0)+1)<>$D$2,"",INDEX(Pedidos_DB!E:E,3+MATCH($D$2,Pedidos_DB!C4:C110,0)+1)),"") -> Condicionador Nutritivo | F11: =IFERROR(IF(INDEX(Pedidos_DB!C:C,3+MATCH($D$2,Pedidos_DB!C4:C110,0)+1)<>$D$2,"",INDEX(Pedidos_DB!F:F,3+MATCH($D$2,Pedidos_DB!C4:C110,0)+1)),"") -> 20 | G11: =IFERROR(IF(INDEX(Pedidos_DB!C:C,3+MATCH($D$2,Pedidos_DB!C4:C110,0)+1)<>$D$2,"",INDEX(Pedidos_DB!G:G,3+MATCH($D$2,Pedidos_DB!C4:C110,0)+1)),"") -> 356 | H11: =IFERROR(IF(INDEX(Pedidos_DB!C:C,3+MATCH($D$2,Pedidos_DB!C4:C110,0)+1)<>$D$2,"",INDEX(Pedidos_DB!H:H,3+MATCH($D$2,Pedidos_DB!C4:C110,0)+1)),"") -> concluído | J11: Salão Glamour | L11: =SUMPRODUCT((Pedidos_DB!C4:C110=$D$2)*(Pedidos_DB!D4:D110=J11)*Pedidos_DB!G4:G110) -> 795.7
B12: =IFERROR(IF(INDEX(Pedidos_DB!C:C,3+MATCH($D$2,Pedidos_DB!C4:C110,0)+2)<>$D$2,"",INDEX(Pedidos_DB!B:B,3+MATCH($D$2,Pedidos_DB!C4:C110,0)+2)),"") -> 2024-09-08 | C12: =IFERROR(IF(INDEX(Pedidos_DB!C:C,3+MATCH($D$2,Pedidos_DB!C4:C110,0)+2)<>$D$2,"",INDEX(Pedidos_DB!C:C,3+MATCH($D$2,Pedidos_DB!C4:C110,0)+2)),"") -> Setembro | D12: =IFERROR(IF(INDEX(Pedidos_DB!C:C,3+MATCH($D$2,Pedidos_DB!C4:C110,0)+2)<>$D$2,"",INDEX(Pedidos_DB!D:D,3+MATCH($D$2,Pedidos_DB!C4:C110,0)+2)),"") -> Salão Beleza & Cia | E12: =IFERROR(IF(INDEX(Pedidos_DB!C:C,3+MATCH($D$2,Pedidos_DB!C4:C110,0)+2)<>$D$2,"",INDEX(Pedidos_DB!E:E,3+MATCH($D$2,Pedidos_DB!C4:C110,0)+2)),"") -> Ampola de Reparação | F12: =IFERROR(IF(INDEX(Pedidos_DB!C:C,3+MATCH($D$2,Pedidos_DB!C4:C110,0)+2)<>$D$2,"",INDEX(Pedidos_DB!F:F,3+MATCH($D$2,Pedidos_DB!C4:C110,0)+2)),"") -> 10 | G12: =IFERROR(IF(INDEX(Pedidos_DB!C:C,3+MATCH($D$2,Pedidos_DB!C4:C110,0)+2)<>$D$2,"",INDEX(Pedidos_DB!G:G,3+MATCH($D$2,Pedidos_DB!C4:C110,0)+2)),"") -> 125 | H12: =IFERROR(IF(INDEX(Pedidos_DB!C:C,3+MATCH($D$2,Pedidos_DB!C4:C110,0)+2)<>$D$2,"",INDEX(Pedidos_DB!H:H,3+MATCH($D$2,Pedidos_DB!C4:C110,0)+2)),"") -> concluído | J12: Salão Luxo Capilar | L12: =SUMPRODUCT((Pedidos_DB!C4:C110=$D$2)*(Pedidos_DB!D4:D110=J12)*Pedidos_DB!G4:G110) -> 685.2
B13: =IFERROR(IF(INDEX(Pedidos_DB!C:C,3+MATCH($D$2,Pedidos_DB!C4:C110,0)+3)<>$D$2,"",INDEX(Pedidos_DB!B:B,3+MATCH($D$2,Pedidos_DB!C4:C110,0)+3)),"") -> 2024-09-10 | C13: =IFERROR(IF(INDEX(Pedidos_DB!C:C,3+MATCH($D$2,Pedidos_DB!C4:C110,0)+3)<>$D$2,"",INDEX(Pedidos_DB!C:C,3+MATCH($D$2,Pedidos_DB!C4:C110,0)+3)),"") -> Setembro | D13: =IFERROR(IF(INDEX(Pedidos_DB!C:C,3+MATCH($D$2,Pedidos_DB!C4:C110,0)+3)<>$D$2,"",INDEX(Pedidos_DB!D:D,3+MATCH($D$2,Pedidos_DB!C4:C110,0)+3)),"") -> Salão Bella Cabelos | E13: =IFERROR(IF(INDEX(Pedidos_DB!C:C,3+MATCH($D$2,Pedidos_DB!C4:C110,0)+3)<>$D$2,"",INDEX(Pedidos_DB!E:E,3+MATCH($D$2,Pedidos_DB!C4:C110,0)+3)),"") -> Máscara de Hidratação | F13: =IFERROR(IF(INDEX(Pedidos_DB!C:C,3+MATCH($D$2,Pedidos_DB!C4:C110,0)+3)<>$D$2,"",INDEX(Pedidos_DB!F:F,3+MATCH($D$2,Pedidos_DB!C4:C110,0)+3)),"") -> 12 | G13: =IFERROR(IF(INDEX(Pedidos_DB!C:C,3+MATCH($D$2,Pedidos_DB!C4:C110,0)+3)<>$D$2,"",INDEX(Pedidos_DB!G:G,3+MATCH($D$2,Pedidos_DB!C4:C110,0)+3)),"") -> 420 | H13: =IFERROR(IF(INDEX(Pedidos_DB!C:C,3+MATCH($D$2,Pedidos_DB!C4:C110,0)+3)<>$D$2,"",INDEX(Pedidos_DB!H:H,3+MATCH($D$2,Pedidos_DB!C4:C110,0)+3)),"") -> concluído | J13: Salão Cabelos de Ouro | L13: =SUMPRODUCT((Pedidos_DB!C4:C110=$D$2)*(Pedidos_DB!D4:D110=J13)*Pedidos_DB!G4:G110) -> 754
B14: =IFERROR(IF(INDEX(Pedidos_DB!C:C,3+MATCH($D$2,Pedidos_DB!C4:C110,0)+4)<>$D$2,"",INDEX(Pedidos_DB!B:B,3+MATCH($D$2,Pedidos_DB!C4:C110,0)+4)),"") -> 2024-09-12 | C14: =IFERROR(IF(INDEX(Pedidos_DB!C:C,3+MATCH($D$2,Pedidos_DB!C4:C110,0)+4)<>$D$2,"",INDEX(Pedidos_DB!C:C,3+MATCH($D$2,Pedidos_DB!C4:C110,0)+4)),"") -> Setembro | D14: =IFERROR(IF(INDEX(Pedidos_DB!C:C,3+MATCH($D$2,Pedidos_DB!C4:C110,0)+4)<>$D$2,"",INDEX(Pedidos_DB!D:D,3+MATCH($D$2,Pedidos_DB!C4:C110,0)+4)),"") -> Salão Luxo Capilar | E14: =IFERROR(IF(INDEX(Pedidos_DB!C:C,3+MATCH($D$2,Pedidos_DB!C4:C110,0)+4)<>$D$2,"",INDEX(Pedidos_DB!E:E,3+MATCH($D$2,Pedidos_DB!C4:C110,0)+4)),"") -> Óleo de Rícino | F14: =IFERROR(IF(INDEX(Pedidos_DB!C:C,3+MATCH($D$2,Pedidos_DB!C4:C110,0)+4)<>$D$2,"",INDEX(Pedidos_DB!F:F,3+MATCH($D$2,Pedidos_DB!C4:C110,0)+4)),"") -> 18 | G14: =IFERROR(IF(INDEX(Pedidos_DB!C:C,3+MATCH($D$2,Pedidos_DB!C4:C110,0)+4)<>$D$2,"",INDEX(Pedidos_DB!G:G,3+MATCH($D$2,Pedidos_DB!C4:C110,0)+4)),"") -> 360 | H14: =IFERROR(IF(INDEX(Pedidos_DB!C:C,3+MATCH($D$2,Pedidos_DB!C4:C110,0)+4)<>$D$2,"",INDEX(Pedidos_DB!H:H,3+MATCH($D$2,Pedidos_DB!C4:C110,0)+4)),"") -> concluído | J14: Salão Bella Cabelos | L14: =SUMPRODUCT((Pedidos_DB!C4:C110=$D$2)*(Pedidos_DB!D4:D110=J14)*Pedidos_DB!G4:G110) -> 771
B15: =IFERROR(IF(INDEX(Pedidos_DB!C:C,3+MATCH($D$2,Pedidos_DB!C4:C110,0)+5)<>$D$2,"",INDEX(Pedidos_DB!B:B,3+MATCH($D$2,Pedidos_DB!C4:C110,0)+5)),"") -> 2024-09-15 | C15: =IFERROR(IF(INDEX(Pedidos_DB!C:C,3+MATCH($D$2,Pedidos_DB!C4:C110,0)+5)<>$D$2,"",INDEX(Pedidos_DB!C:C,3+MATCH($D$2,Pedidos_DB!C4:C110,0)+5)),"") -> Setembro | D15: =IFERROR(IF(INDEX(Pedidos_DB!C:C,3+MATCH($D$2,Pedidos_DB!C4:C110,0)+5)<>$D$2,"",INDEX(Pedidos_DB!D:D,3+MATCH($D$2,Pedidos_DB!C4:C110,0)+5)),"") -> Salão Glamour | E15: =IFERROR(IF(INDEX(Pedidos_DB!C:C,3+MATCH($D$2,Pedidos_DB!C4:C110,0)+5)<>$D$2,"",INDEX(Pedidos_DB!E:E,3+MATCH($D$2,Pedidos_DB!C4:C110,0)+5)),"") -> Creme de Pentear Hidratante | F15: =IFERROR(IF(INDEX(Pedidos_DB!C:C,3+MATCH($D$2,Pedidos_DB!C4:C110,0)+5)<>$D$2,"",INDEX(Pedidos_DB!F:F,3+MATCH($D$2,Pedidos_DB!C4:C110,0)+5)),"") -> 15 | G15: =IFERROR(IF(INDEX(Pedidos_DB!C:C,3+MATCH($D$2,Pedidos_DB!C4:C110,0)+5)<>$D$2,"",INDEX(Pedidos_DB!G:G,3+MATCH($D$2,Pedidos_DB!C4:C110,0)+5)),"") -> 273 | H15: =IFERROR(IF(INDEX(Pedidos_DB!C:C,3+MATCH($D$2,Pedidos_DB!C4:C110,0)+5)<>$D$2,"",INDEX(Pedidos_DB!H:H,3+MATCH($D$2,Pedidos_DB!C4:C110,0)+5)),"") -> concluído
B16: =IFERROR(IF(INDEX(Pedidos_DB!C:C,3+MATCH($D$2,Pedidos_DB!C4:C110,0)+6)<>$D$2,"",INDEX(Pedidos_DB!B:B,3+MATCH($D$2,Pedidos_DB!C4:C110,0)+6)),"") -> 2024-09-17 | C16: =IFERROR(IF(INDEX(Pedidos_DB!C:C,3+MATCH($D$2,Pedidos_DB!C4:C110,0)+6)<>$D$2,"",INDEX(Pedidos_DB!C:C,3+MATCH($D$2,Pedidos_DB!C4:C110,0)+6)),"") -> Setembro | D16: =IFERROR(IF(INDEX(Pedidos_DB!C:C,3+MATCH($D$2,Pedidos_DB!C4:C110,0)+6)<>$D$2,"",INDEX(Pedidos_DB!D:D,3+MATCH($D$2,Pedidos_DB!C4:C110,0)+6)),"") -> Salão Cabelos de Ouro | E16: =IFERROR(IF(INDEX(Pedidos_DB!C:C,3+MATCH($D$2,Pedidos_DB!C4:C110,0)+6)<>$D$2,"",INDEX(Pedidos_DB!E:E,3+MATCH($D$2,Pedidos_DB!C4:C110,0)+6)),"") -> Shampoo Detox | F16: =IFERROR(IF(INDEX(Pedidos_DB!C:C,3+MATCH($D$2,Pedidos_DB!C4:C110,0)+6)<>$D$2,"",INDEX(Pedidos_DB!F:F,3+MATCH($D$2,Pedidos_DB!C4:C110,0)+6)),"") -> 20 | G16: =IFERROR(IF(INDEX(Pedidos_DB!C:C,3+MATCH($D$2,Pedidos_DB!C4:C110,0)+6)<>$D$2,"",INDEX(Pedidos_DB!G:G,3+MATCH($D$2,Pedidos_DB!C4:C110,0)+6)),"") -> 398 | H16: =IFERROR(IF(INDEX(Pedidos_DB!C:C,3+MATCH($D$2,Pedidos_DB!C4:C110,0)+6)<>$D$2,"",INDEX(Pedidos_DB!H:H,3+MATCH($D$2,Pedidos_DB!C4:C110,0)+6)),"") -> concluído
B17: =IFERROR(IF(INDEX(Pedidos_DB!C:C,3+MATCH($D$2,Pedidos_DB!C4:C110,0)+7)<>$D$2,"",INDEX(Pedidos_DB!B:B,3+MATCH($D$2,Pedidos_DB!C4:C110,0)+7)),"") -> 2024-09-20 | C17: =IFERROR(IF(INDEX(Pedidos_DB!C:C,3+MATCH($D$2,Pedidos_DB!C4:C110,0)+7)<>$D$2,"",INDEX(Pedidos_DB!C:C,3+MATCH($D$2,Pedidos_DB!C4:C110,0)+7)),"") -> Setembro | D17: =IFERROR(IF(INDEX(Pedidos_DB!C:C,3+MATCH($D$2,Pedidos_DB!C4:C110,0)+7)<>$D$2,"",INDEX(Pedidos_DB!D:D,3+MATCH($D$2,Pedidos_DB!C4:C110,0)+7)),"") -> Salão Beleza & Cia | E17: =IFERROR(IF(INDEX(Pedidos_DB!C:C,3+MATCH($D$2,Pedidos_DB!C4:C110,0)+7)<>$D$2,"",INDEX(Pedidos_DB!E:E,3+MATCH($D$2,Pedidos_DB!C4:C110,0)+7)),"") -> Máscara de Nutrição Profunda | F17: =IFERROR(IF(INDEX(Pedidos_DB!C:C,3+MATCH($D$2,Pedidos_DB!C4:C110,0)+7)<>$D$2,"",INDEX(Pedidos_DB!F:F,3+MATCH($D$2,Pedidos_DB!C4:C110,0)+7)),"") -> 10 | G17: =IFERROR(IF(INDEX(Pedidos_DB!C:C,3+MATCH($D$2,Pedidos_DB!C4:C110,0)+7)<>$D$2,"",INDEX(Pedidos_DB!G:G,3+MATCH($D$2,Pedidos_DB!C4:C110,0)+7)),"") -> 420 | H17: =IFERROR(IF(INDEX(Pedidos_DB!C:C,3+MATCH($D$2,Pedidos_DB!C4:C110,0)+7)<>$D$2,"",INDEX(Pedidos_DB!H:H,3+MATCH($D$2,Pedidos_DB!C4:C110,0)+7)),"") -> concluído
B18: =IFERROR(IF(INDEX(Pedidos_DB!C:C,3+MATCH($D$2,Pedidos_DB!C4:C110,0)+8)<>$D$2,"",INDEX(Pedidos_DB!B:B,3+MATCH($D$2,Pedidos_DB!C4:C110,0)+8)),"") -> 2024-09-22 | C18: =IFERROR(IF(INDEX(Pedidos_DB!C:C,3+MATCH($D$2,Pedidos_DB!C4:C110,0)+8)<>$D$2,"",INDEX(Pedidos_DB!C:C,3+MATCH($D$2,Pedidos_DB!C4:C110,0)+8)),"") -> Setembro | D18: =IFERROR(IF(INDEX(Pedidos_DB!C:C,3+MATCH($D$2,Pedidos_DB!C4:C110,0)+8)<>$D$2,"",INDEX(Pedidos_DB!D:D,3+MATCH($D$2,Pedidos_DB!C4:C110,0)+8)),"") -> Salão Bella Cabelos | E18: =IFERROR(IF(INDEX(Pedidos_DB!C:C,3+MATCH($D$2,Pedidos_DB!C4:C110,0)+8)<>$D$2,"",INDEX(Pedidos_DB!E:E,3+MATCH($D$2,Pedidos_DB!C4:C110,0)+8)),"") -> Leave-in Nutritivo | F18: =IFERROR(IF(INDEX(Pedidos_DB!C:C,3+MATCH($D$2,Pedidos_DB!C4:C110,0)+8)<>$D$2,"",INDEX(Pedidos_DB!F:F,3+MATCH($D$2,Pedidos_DB!C4:C110,0)+8)),"") -> 15 | G18: =IFERROR(IF(INDEX(Pedidos_DB!C:C,3+MATCH($D$2,Pedidos_DB!C4:C110,0)+8)<>$D$2,"",INDEX(Pedidos_DB!G:G,3+MATCH($D$2,Pedidos_DB!C4:C110,0)+8)),"") -> 351 | H18: =IFERROR(IF(INDEX(Pedidos_DB!C:C,3+MATCH($D$2,Pedidos_DB!C4:C110,0)+8)<>$D$2,"",INDEX(Pedidos_DB!H:H,3+MATCH($D$2,Pedidos_DB!C4:C110,0)+8)),"") -> concluído
B19: =IFERROR(IF(INDEX(Pedidos_DB!C:C,3+MATCH($D$2,Pedidos_DB!C4:C110,0)+9)<>$D$2,"",INDEX(Pedidos_DB!B:B,3+MATCH($D$2,Pedidos_DB!C4:C110,0)+9)),"") -> 2024-09-25 | C19: =IFERROR(IF(INDEX(Pedidos_DB!C:C,3+MATCH($D$2,Pedidos_DB!C4:C110,0)+9)<>$D$2,"",INDEX(Pedidos_DB!C:C,3+MATCH($D$2,Pedidos_DB!C4:C110,0)+9)),"") -> Setembro | D19: =IFERROR(IF(INDEX(Pedidos_DB!C:C,3+MATCH($D$2,Pedidos_DB!C4:C110,0)+9)<>$D$2,"",INDEX(Pedidos_DB!D:D,3+MATCH($D$2,Pedidos_DB!C4:C110,0)+9)),"") -> Salão Luxo Capilar | E19: =IFERROR(IF(INDEX(Pedidos_DB!C:C,3+MATCH($D$2,Pedidos_DB!C4:C110,0)+9)<>$D$2,"",INDEX(Pedidos_DB!E:E,3+MATCH($D$2,Pedidos_DB!C4:C110,0)+9)),"") -> Condicionador Antifrizz | F19: =IFERROR(IF(INDEX(Pedidos_DB!C:C,3+MATCH($D$2,Pedidos_DB!C4:C110,0)+9)<>$D$2,"",INDEX(Pedidos_DB!F:F,3+MATCH($D$2,Pedidos_DB!C4:C110,0)+9)),"") -> 12 | G19: =IFERROR(IF(INDEX(Pedidos_DB!C:C,3+MATCH($D$2,Pedidos_DB!C4:C110,0)+9)<>$D$2,"",INDEX(Pedidos_DB!G:G,3+MATCH($D$2,Pedidos_DB!C4:C110,0)+9)),"") -> 325.2 | H19: =IFERROR(IF(INDEX(Pedidos_DB!C:C,3+MATCH($D$2,Pedidos_DB!C4:C110,0)+9)<>$D$2,"",INDEX(Pedidos_DB!H:H,3+MATCH($D$2,Pedidos_DB!C4:C110,0)+9)),"") -> concluído
B20: =IFERROR(IF(INDEX(Pedidos_DB!C:C,3+MATCH($D$2,Pedidos_DB!C4:C110,0)+10)<>$D$2,"",INDEX(Pedidos_DB!B:B,3+MATCH($D$2,Pedidos_DB!C4:C110,0)+10)),"") -> 2024-09-27 | C20: =IFERROR(IF(INDEX(Pedidos_DB!C:C,3+MATCH($D$2,Pedidos_DB!C4:C110,0)+10)<>$D$2,"",INDEX(Pedidos_DB!C:C,3+MATCH($D$2,Pedidos_DB!C4:C110,0)+10)),"") -> Setembro | D20: =IFERROR(IF(INDEX(Pedidos_DB!C:C,3+MATCH($D$2,Pedidos_DB!C4:C110,0)+10)<>$D$2,"",INDEX(Pedidos_DB!D:D,3+MATCH($D$2,Pedidos_DB!C4:C110,0)+10)),"") -> Salão Glamour | E20: =IFERROR(IF(INDEX(Pedidos_DB!C:C,3+MATCH($D$2,Pedidos_DB!C4:C110,0)+10)<>$D$2,"",INDEX(Pedidos_DB!E:E,3+MATCH($D$2,Pedidos_DB!C4:C110,0)+10)),"") -> Óleo de Argan | F20: =IFERROR(IF(INDEX(Pedidos_DB!C:C,3+MATCH($D$2,Pedidos_DB!C4:C110,0)+10)<>$D$2,"",INDEX(Pedidos_DB!F:F,3+MATCH($D$2,Pedidos_DB!C4:C110,0)+10)),"") -> 8 | G20: =IFERROR(IF(INDEX(Pedidos_DB!C:C,3+MATCH($D$2,Pedidos_DB!C4:C110,0)+10)<>$D$2,"",INDEX(Pedidos_DB!G:G,3+MATCH($D$2,Pedidos_DB!C4:C110,0)+10)),"") -> 239.2 | H20: =IFERROR(IF(INDEX(Pedidos_DB!C:C,3+MATCH($D$2,Pedidos_DB!C4:C110,0)+10)<>$D$2,"",INDEX(Pedidos_DB!H:H,3+MATCH($D$2,Pedidos_DB!C4:C110,0)+10)),"") -> concluído
B21: =IFERROR(IF(INDEX(Pedidos_DB!C:C,3+MATCH($D$2,Pedidos_DB!C4:C110,0)+11)<>$D$2,"",INDEX(Pedidos_DB!B:B,3+MATCH($D$2,Pedidos_DB!C4:C110,0)+11)),"") | C21: =IFERROR(IF(INDEX(Pedidos_DB!C:C,3+MATCH($D$2,Pedidos_DB!C4:C110,0)+11)<>$D$2,"",INDEX(Pedidos_DB!C:C,3+MATCH($D$2,Pedidos_DB!C4:C110,0)+11)),"") | D21: =IFERROR(IF(INDEX(Pedidos_DB!C:C,3+MATCH($D$2,Pedidos_DB!C4:C110,0)+11)<>$D$2,"",INDEX(Pedidos_DB!D:D,3+MATCH($D$2,Pedidos_DB!C4:C110,0)+11)),"") | E21: =IFERROR(IF(INDEX(Pedidos_DB!C:C,3+MATCH($D$2,Pedidos_DB!C4:C110,0)+11)<>$D$2,"",INDEX(Pedidos_DB!E:E,3+MATCH($D$2,Pedidos_DB!C4:C110,0)+11)),"") | F21: =IFERROR(IF(INDEX(Pedidos_DB!C:C,3+MATCH($D$2,Pedidos_DB!C4:C110,0)+11)<>$D$2,"",INDEX(Pedidos_DB!F:F,3+MATCH($D$2,Pedidos_DB!C4:C110,0)+11)),"") | G21: =IFERROR(IF(INDEX(Pedidos_DB!C:C,3+MATCH($D$2,Pedidos_DB!C4:C110,0)+11)<>$D$2,"",INDEX(Pedidos_DB!G:G,3+MATCH($D$2,Pedidos_DB!C4:C110,0)+11)),"") | H21: =IFERROR(IF(INDEX(Pedidos_DB!C:C,3+MATCH($D$2,Pedidos_DB!C4:C110,0)+11)<>$D$2,"",INDEX(Pedidos_DB!H:H,3+MATCH($D$2,Pedidos_DB!C4:C110,0)+11)),"")
B22: =IFERROR(IF(INDEX(Pedidos_DB!C:C,3+MATCH($D$2,Pedidos_DB!C4:C110,0)+12)<>$D$2,"",INDEX(Pedidos_DB!B:B,3+MATCH($D$2,Pedidos_DB!C4:C110,0)+12)),"") | C22: =IFERROR(IF(INDEX(Pedidos_DB!C:C,3+MATCH($D$2,Pedidos_DB!C4:C110,0)+12)<>$D$2,"",INDEX(Pedidos_DB!C:C,3+MATCH($D$2,Pedidos_DB!C4:C110,0)+12)),"") | D22: =IFERROR(IF(INDEX(Pedidos_DB!C:C,3+MATCH($D$2,Pedidos_DB!C4:C110,0)+12)<>$D$2,"",INDEX(Pedidos_DB!D:D,3+MATCH($D$2,Pedidos_DB!C4:C110,0)+12)),"") | E22: =IFERROR(IF(INDEX(Pedidos_DB!C:C,3+MATCH($D$2,Pedidos_DB!C4:C110,0)+12)<>$D$2,"",INDEX(Pedidos_DB!E:E,3+MATCH($D$2,Pedidos_DB!C4:C110,0)+12)),"") | F22: =IFERROR(IF(INDEX(Pedidos_DB!C:C,3+MATCH($D$2,Pedidos_DB!C4:C110,0)+12)<>$D$2,"",INDEX(Pedidos_DB!F:F,3+MATCH($D$2,Pedidos_DB!C4:C110,0)+12)),"") | G22: =IFERROR(IF(INDEX(Pedidos_DB!C:C,3+MATCH($D$2,Pedidos_DB!C4:C110,0)+12)<>$D$2,"",INDEX(Pedidos_DB!G:G,3+MATCH($D$2,Pedidos_DB!C4:C110,0)+12)),"") | H22: =IFERROR(IF(INDEX(Pedidos_DB!C:C,3+MATCH($D$2,Pedidos_DB!C4:C110,0)+12)<>$D$2,"",INDEX(Pedidos_DB!H:H,3+MATCH($D$2,Pedidos_DB!C4:C110,0)+12)),"")
B23: =IFERROR(IF(INDEX(Pedidos_DB!C:C,3+MATCH($D$2,Pedidos_DB!C4:C110,0)+13)<>$D$2,"",INDEX(Pedidos_DB!B:B,3+MATCH($D$2,Pedidos_DB!C4:C110,0)+13)),"") | C23: =IFERROR(IF(INDEX(Pedidos_DB!C:C,3+MATCH($D$2,Pedidos_DB!C4:C110,0)+13)<>$D$2,"",INDEX(Pedidos_DB!C:C,3+MATCH($D$2,Pedidos_DB!C4:C110,0)+13)),"") | D23: =IFERROR(IF(INDEX(Pedidos_DB!C:C,3+MATCH($D$2,Pedidos_DB!C4:C110,0)+13)<>$D$2,"",INDEX(Pedidos_DB!D:D,3+MATCH($D$2,Pedidos_DB!C4:C110,0)+13)),"") | E23: =IFERROR(IF(INDEX(Pedidos_DB!C:C,3+MATCH($D$2,Pedidos_DB!C4:C110,0)+13)<>$D$2,"",INDEX(Pedidos_DB!E:E,3+MATCH($D$2,Pedidos_DB!C4:C110,0)+13)),"") | F23: =IFERROR(IF(INDEX(Pedidos_DB!C:C,3+MATCH($D$2,Pedidos_DB!C4:C110,0)+13)<>$D$2,"",INDEX(Pedidos_DB!F:F,3+MATCH($D$2,Pedidos_DB!C4:C110,0)+13)),"") | G23: =IFERROR(IF(INDEX(Pedidos_DB!C:C,3+MATCH($D$2,Pedidos_DB!C4:C110,0)+13)<>$D$2,"",INDEX(Pedidos_DB!G:G,3+MATCH($D$2,Pedidos_DB!C4:C110,0)+13)),"") | H23: =IFERROR(IF(INDEX(Pedidos_DB!C:C,3+MATCH($D$2,Pedidos_DB!C4:C110,0)+13)<>$D$2,"",INDEX(Pedidos_DB!H:H,3+MATCH($D$2,Pedidos_DB!C4:C110,0)+13)),"")
B24: =IFERROR(IF(INDEX(Pedidos_DB!C:C,3+MATCH($D$2,Pedidos_DB!C4:C110,0)+14)<>$D$2,"",INDEX(Pedidos_DB!B:B,3+MATCH($D$2,Pedidos_DB!C4:C110,0)+14)),"") | C24: =IFERROR(IF(INDEX(Pedidos_DB!C:C,3+MATCH($D$2,Pedidos_DB!C4:C110,0)+14)<>$D$2,"",INDEX(Pedidos_DB!C:C,3+MATCH($D$2,Pedidos_DB!C4:C110,0)+14)),"") | D24: =IFERROR(IF(INDEX(Pedidos_DB!C:C,3+MATCH($D$2,Pedidos_DB!C4:C110,0)+14)<>$D$2,"",INDEX(Pedidos_DB!D:D,3+MATCH($D$2,Pedidos_DB!C4:C110,0)+14)),"") | E24: =IFERROR(IF(INDEX(Pedidos_DB!C:C,3+MATCH($D$2,Pedidos_DB!C4:C110,0)+14)<>$D$2,"",INDEX(Pedidos_DB!E:E,3+MATCH($D$2,Pedidos_DB!C4:C110,0)+14)),"") | F24: =IFERROR(IF(INDEX(Pedidos_DB!C:C,3+MATCH($D$2,Pedidos_DB!C4:C110,0)+14)<>$D$2,"",INDEX(Pedidos_DB!F:F,3+MATCH($D$2,Pedidos_DB!C4:C110,0)+14)),"") | G24: =IFERROR(IF(INDEX(Pedidos_DB!C:C,3+MATCH($D$2,Pedidos_DB!C4:C110,0)+14)<>$D$2,"",INDEX(Pedidos_DB!G:G,3+MATCH($D$2,Pedidos_DB!C4:C110,0)+14)),"") | H24: =IFERROR(IF(INDEX(Pedidos_DB!C:C,3+MATCH($D$2,Pedidos_DB!C4:C110,0)+14)<>$D$2,"",INDEX(Pedidos_DB!H:H,3+MATCH($D$2,Pedidos_DB!C4:C110,0)+14)),"")
B25: =IFERROR(IF(INDEX(Pedidos_DB!C:C,3+MATCH($D$2,Pedidos_DB!C4:C110,0)+15)<>$D$2,"",INDEX(Pedidos_DB!B:B,3+MATCH($D$2,Pedidos_DB!C4:C110,0)+15)),"") | C25: =IFERROR(IF(INDEX(Pedidos_DB!C:C,3+MATCH($D$2,Pedidos_DB!C4:C110,0)+15)<>$D$2,"",INDEX(Pedidos_DB!C:C,3+MATCH($D$2,Pedidos_DB!C4:C110,0)+15)),"") | D25: =IFERROR(IF(INDEX(Pedidos_DB!C:C,3+MATCH($D$2,Pedidos_DB!C4:C110,0)+15)<>$D$2,"",INDEX(Pedidos_DB!D:D,3+MATCH($D$2,Pedidos_DB!C4:C110,0)+15)),"") | E25: =IFERROR(IF(INDEX(Pedidos_DB!C:C,3+MATCH($D$2,Pedidos_DB!C4:C110,0)+15)<>$D$2,"",INDEX(Pedidos_DB!E:E,3+MATCH($D$2,Pedidos_DB!C4:C110,0)+15)),"") | F25: =IFERROR(IF(INDEX(Pedidos_DB!C:C,3+MATCH($D$2,Pedidos_DB!C4:C110,0)+15)<>$D$2,"",INDEX(Pedidos_DB!F:F,3+MATCH($D$2,Pedidos_DB!C4:C110,0)+15)),"") | G25: =IFERROR(IF(INDEX(Pedidos_DB!C:C,3+MATCH($D$2,Pedidos_DB!C4:C110,0)+15)<>$D$2,"",INDEX(Pedidos_DB!G:G,3+MATCH($D$2,Pedidos_DB!C4:C110,0)+15)),"") | H25: =IFERROR(IF(INDEX(Pedidos_DB!C:C,3+MATCH($D$2,Pedidos_DB!C4:C110,0)+15)<>$D$2,"",INDEX(Pedidos_DB!H:H,3+MATCH($D$2,Pedidos_DB!C4:C110,0)+15)),"")
B26: =IFERROR(IF(INDEX(Pedidos_DB!C:C,3+MATCH($D$2,Pedidos_DB!C4:C110,0)+16)<>$D$2,"",INDEX(Pedidos_DB!B:B,3+MATCH($D$2,Pedidos_DB!C4:C110,0)+16)),"") | C26: =IFERROR(IF(INDEX(Pedidos_DB!C:C,3+MATCH($D$2,Pedidos_DB!C4:C110,0)+16)<>$D$2,"",INDEX(Pedidos_DB!C:C,3+MATCH($D$2,Pedidos_DB!C4:C110,0)+16)),"") | D26: =IFERROR(IF(INDEX(Pedidos_DB!C:C,3+MATCH($D$2,Pedidos_DB!C4:C110,0)+16)<>$D$2,"",INDEX(Pedidos_DB!D:D,3+MATCH($D$2,Pedidos_DB!C4:C110,0)+16)),"") | E26: =IFERROR(IF(INDEX(Pedidos_DB!C:C,3+MATCH($D$2,Pedidos_DB!C4:C110,0)+16)<>$D$2,"",INDEX(Pedidos_DB!E:E,3+MATCH($D$2,Pedidos_DB!C4:C110,0)+16)),"") | F26: =IFERROR(IF(INDEX(Pedidos_DB!C:C,3+MATCH($D$2,Pedidos_DB!C4:C110,0)+16)<>$D$2,"",INDEX(Pedidos_DB!F:F,3+MATCH($D$2,Pedidos_DB!C4:C110,0)+16)),"") | G26: =IFERROR(IF(INDEX(Pedidos_DB!C:C,3+MATCH($D$2,Pedidos_DB!C4:C110,0)+16)<>$D$2,"",INDEX(Pedidos_DB!G:G,3+MATCH($D$2,Pedidos_DB!C4:C110,0)+16)),"") | H26: =IFERROR(IF(INDEX(Pedidos_DB!C:C,3+MATCH($D$2,Pedidos_DB!C4:C110,0)+16)<>$D$2,"",INDEX(Pedidos_DB!H:H,3+MATCH($D$2,Pedidos_DB!C4:C110,0)+16)),"")
B27: =IFERROR(IF(INDEX(Pedidos_DB!C:C,3+MATCH($D$2,Pedidos_DB!C4:C110,0)+17)<>$D$2,"",INDEX(Pedidos_DB!B:B,3+MATCH($D$2,Pedidos_DB!C4:C110,0)+17)),"") | C27: =IFERROR(IF(INDEX(Pedidos_DB!C:C,3+MATCH($D$2,Pedidos_DB!C4:C110,0)+17)<>$D$2,"",INDEX(Pedidos_DB!C:C,3+MATCH($D$2,Pedidos_DB!C4:C110,0)+17)),"") | D27: =IFERROR(IF(INDEX(Pedidos_DB!C:C,3+MATCH($D$2,Pedidos_DB!C4:C110,0)+17)<>$D$2,"",INDEX(Pedidos_DB!D:D,3+MATCH($D$2,Pedidos_DB!C4:C110,0)+17)),"") | E27: =IFERROR(IF(INDEX(Pedidos_DB!C:C,3+MATCH($D$2,Pedidos_DB!C4:C110,0)+17)<>$D$2,"",INDEX(Pedidos_DB!E:E,3+MATCH($D$2,Pedidos_DB!C4:C110,0)+17)),"") | F27: =IFERROR(IF(INDEX(Pedidos_DB!C:C,3+MATCH($D$2,Pedidos_DB!C4:C110,0)+17)<>$D$2,"",INDEX(Pedidos_DB!F:F,3+MATCH($D$2,Pedidos_DB!C4:C110,0)+17)),"") | G27: =IFERROR(IF(INDEX(Pedidos_DB!C:C,3+MATCH($D$2,Pedidos_DB!C4:C110,0)+17)<>$D$2,"",INDEX(Pedidos_DB!G:G,3+MATCH($D$2,Pedidos_DB!C4:C110,0)+17)),"") | H27: =IFERROR(IF(INDEX(Pedidos_DB!C:C,3+MATCH($D$2,Pedidos_DB!C4:C110,0)+17)<>$D$2,"",INDEX(Pedidos_DB!H:H,3+MATCH($D$2,Pedidos_DB!C4:C110,0)+17)),"")
B28: =IFERROR(IF(INDEX(Pedidos_DB!C:C,3+MATCH($D$2,Pedidos_DB!C4:C110,0)+18)<>$D$2,"",INDEX(Pedidos_DB!B:B,3+MATCH($D$2,Pedidos_DB!C4:C110,0)+18)),"") | C28: =IFERROR(IF(INDEX(Pedidos_DB!C:C,3+MATCH($D$2,Pedidos_DB!C4:C110,0)+18)<>$D$2,"",INDEX(Pedidos_DB!C:C,3+MATCH($D$2,Pedidos_DB!C4:C110,0)+18)),"") | D28: =IFERROR(IF(INDEX(Pedidos_DB!C:C,3+MATCH($D$2,Pedidos_DB!C4:C110,0)+18)<>$D$2,"",INDEX(Pedidos_DB!D:D,3+MATCH($D$2,Pedidos_DB!C4:C110,0)+18)),"") | E28: =IFERROR(IF(INDEX(Pedidos_DB!C:C,3+MATCH($D$2,Pedidos_DB!C4:C110,0)+18)<>$D$2,"",INDEX(Pedidos_DB!E:E,3+MATCH($D$2,Pedidos_DB!C4:C110,0)+18)),"") | F28: =IFERROR(IF(INDEX(Pedidos_DB!C:C,3+MATCH($D$2,Pedidos_DB!C4:C110,0)+18)<>$D$2,"",INDEX(Pedidos_DB!F:F,3+MATCH($D$2,Pedidos_DB!C4:C110,0)+18)),"") | G28: =IFERROR(IF(INDEX(Pedidos_DB!C:C,3+MATCH($D$2,Pedidos_DB!C4:C110,0)+18)<>$D$2,"",INDEX(Pedidos_DB!G:G,3+MATCH($D$2,Pedidos_DB!C4:C110,0)+18)),"") | H28: =IFERROR(IF(INDEX(Pedidos_DB!C:C,3+MATCH($D$2,Pedidos_DB!C4:C110,0)+18)<>$D$2,"",INDEX(Pedidos_DB!H:H,3+MATCH($D$2,Pedidos_DB!C4:C110,0)+18)),"")
B29: =IFERROR(IF(INDEX(Pedidos_DB!C:C,3+MATCH($D$2,Pedidos_DB!C4:C110,0)+19)<>$D$2,"",INDEX(Pedidos_DB!B:B,3+MATCH($D$2,Pedidos_DB!C4:C110,0)+19)),"") | C29: =IFERROR(IF(INDEX(Pedidos_DB!C:C,3+MATCH($D$2,Pedidos_DB!C4:C110,0)+19)<>$D$2,"",INDEX(Pedidos_DB!C:C,3+MATCH($D$2,Pedidos_DB!C4:C110,0)+19)),"") | D29: =IFERROR(IF(INDEX(Pedidos_DB!C:C,3+MATCH($D$2,Pedidos_DB!C4:C110,0)+19)<>$D$2,"",INDEX(Pedidos_DB!D:D,3+MATCH($D$2,Pedidos_DB!C4:C110,0)+19)),"") | E29: =IFERROR(IF(INDEX(Pedidos_DB!C:C,3+MATCH($D$2,Pedidos_DB!C4:C110,0)+19)<>$D$2,"",INDEX(Pedidos_DB!E:E,3+MATCH($D$2,Pedidos_DB!C4:C110,0)+19)),"") | F29: =IFERROR(IF(INDEX(Pedidos_DB!C:C,3+MATCH($D$2,Pedidos_DB!C4:C110,0)+19)<>$D$2,"",INDEX(Pedidos_DB!F:F,3+MATCH($D$2,Pedidos_DB!C4:C110,0)+19)),"") | G29: =IFERROR(IF(INDEX(Pedidos_DB!C:C,3+MATCH($D$2,Pedidos_DB!C4:C110,0)+19)<>$D$2,"",INDEX(Pedidos_DB!G:G,3+MATCH($D$2,Pedidos_DB!C4:C110,0)+19)),"") | H29: =IFERROR(IF(INDEX(Pedidos_DB!C:C,3+MATCH($D$2,Pedidos_DB!C4:C110,0)+19)<>$D$2,"",INDEX(Pedidos_DB!H:H,3+MATCH($D$2,Pedidos_DB!C4:C110,0)+19)),"")
B30: =IFERROR(IF(INDEX(Pedidos_DB!C:C,3+MATCH($D$2,Pedidos_DB!C4:C110,0)+20)<>$D$2,"",INDEX(Pedidos_DB!B:B,3+MATCH($D$2,Pedidos_DB!C4:C110,0)+20)),"") | C30: =IFERROR(IF(INDEX(Pedidos_DB!C:C,3+MATCH($D$2,Pedidos_DB!C4:C110,0)+20)<>$D$2,"",INDEX(Pedidos_DB!C:C,3+MATCH($D$2,Pedidos_DB!C4:C110,0)+20)),"") | D30: =IFERROR(IF(INDEX(Pedidos_DB!C:C,3+MATCH($D$2,Pedidos_DB!C4:C110,0)+20)<>$D$2,"",INDEX(Pedidos_DB!D:D,3+MATCH($D$2,Pedidos_DB!C4:C110,0)+20)),"") | E30: =IFERROR(IF(INDEX(Pedidos_DB!C:C,3+MATCH($D$2,Pedidos_DB!C4:C110,0)+20)<>$D$2,"",INDEX(Pedidos_DB!E:E,3+MATCH($D$2,Pedidos_DB!C4:C110,0)+20)),"") | F30: =IFERROR(IF(INDEX(Pedidos_DB!C:C,3+MATCH($D$2,Pedidos_DB!C4:C110,0)+20)<>$D$2,"",INDEX(Pedidos_DB!F:F,3+MATCH($D$2,Pedidos_DB!C4:C110,0)+20)),"") | G30: =IFERROR(IF(INDEX(Pedidos_DB!C:C,3+MATCH($D$2,Pedidos_DB!C4:C110,0)+20)<>$D$2,"",INDEX(Pedidos_DB!G:G,3+MATCH($D$2,Pedidos_DB!C4:C110,0)+20)),"") | H30: =IFERROR(IF(INDEX(Pedidos_DB!C:C,3+MATCH($D$2,Pedidos_DB!C4:C110,0)+20)<>$D$2,"",INDEX(Pedidos_DB!H:H,3+MATCH($D$2,Pedidos_DB!C4:C110,0)+20)),"")
B31: =IFERROR(IF(INDEX(Pedidos_DB!C:C,3+MATCH($D$2,Pedidos_DB!C4:C110,0)+21)<>$D$2,"",INDEX(Pedidos_DB!B:B,3+MATCH($D$2,Pedidos_DB!C4:C110,0)+21)),"") | C31: =IFERROR(IF(INDEX(Pedidos_DB!C:C,3+MATCH($D$2,Pedidos_DB!C4:C110,0)+21)<>$D$2,"",INDEX(Pedidos_DB!C:C,3+MATCH($D$2,Pedidos_DB!C4:C110,0)+21)),"") | D31: =IFERROR(IF(INDEX(Pedidos_DB!C:C,3+MATCH($D$2,Pedidos_DB!C4:C110,0)+21)<>$D$2,"",INDEX(Pedidos_DB!D:D,3+MATCH($D$2,Pedidos_DB!C4:C110,0)+21)),"") | E31: =IFERROR(IF(INDEX(Pedidos_DB!C:C,3+MATCH($D$2,Pedidos_DB!C4:C110,0)+21)<>$D$2,"",INDEX(Pedidos_DB!E:E,3+MATCH($D$2,Pedidos_DB!C4:C110,0)+21)),"") | F31: =IFERROR(IF(INDEX(Pedidos_DB!C:C,3+MATCH($D$2,Pedidos_DB!C4:C110,0)+21)<>$D$2,"",INDEX(Pedidos_DB!F:F,3+MATCH($D$2,Pedidos_DB!C4:C110,0)+21)),"") | G31: =IFERROR(IF(INDEX(Pedidos_DB!C:C,3+MATCH($D$2,Pedidos_DB!C4:C110,0)+21)<>$D$2,"",INDEX(Pedidos_DB!G:G,3+MATCH($D$2,Pedidos_DB!C4:C110,0)+21)),"") | H31: =IFERROR(IF(INDEX(Pedidos_DB!C:C,3+MATCH($D$2,Pedidos_DB!C4:C110,0)+21)<>$D$2,"",INDEX(Pedidos_DB!H:H,3+MATCH($D$2,Pedidos_DB!C4:C110,0)+21)),"")
B32: =IFERROR(IF(INDEX(Pedidos_DB!C:C,3+MATCH($D$2,Pedidos_DB!C4:C110,0)+22)<>$D$2,"",INDEX(Pedidos_DB!B:B,3+MATCH($D$2,Pedidos_DB!C4:C110,0)+22)),"") | C32: =IFERROR(IF(INDEX(Pedidos_DB!C:C,3+MATCH($D$2,Pedidos_DB!C4:C110,0)+22)<>$D$2,"",INDEX(Pedidos_DB!C:C,3+MATCH($D$2,Pedidos_DB!C4:C110,0)+22)),"") | D32: =IFERROR(IF(INDEX(Pedidos_DB!C:C,3+MATCH($D$2,Pedidos_DB!C4:C110,0)+22)<>$D$2,"",INDEX(Pedidos_DB!D:D,3+MATCH($D$2,Pedidos_DB!C4:C110,0)+22)),"") | E32: =IFERROR(IF(INDEX(Pedidos_DB!C:C,3+MATCH($D$2,Pedidos_DB!C4:C110,0)+22)<>$D$2,"",INDEX(Pedidos_DB!E:E,3+MATCH($D$2,Pedidos_DB!C4:C110,0)+22)),"") | F32: =IFERROR(IF(INDEX(Pedidos_DB!C:C,3+MATCH($D$2,Pedidos_DB!C4:C110,0)+22)<>$D$2,"",INDEX(Pedidos_DB!F:F,3+MATCH($D$2,Pedidos_DB!C4:C110,0)+22)),"") | G32: =IFERROR(IF(INDEX(Pedidos_DB!C:C,3+MATCH($D$2,Pedidos_DB!C4:C110,0)+22)<>$D$2,"",INDEX(Pedidos_DB!G:G,3+MATCH($D$2,Pedidos_DB!C4:C110,0)+22)),"") | H32: =IFERROR(IF(INDEX(Pedidos_DB!C:C,3+MATCH($D$2,Pedidos_DB!C4:C110,0)+22)<>$D$2,"",INDEX(Pedidos_DB!H:H,3+MATCH($D$2,Pedidos_DB!C4:C110,0)+22)),"")
B33: =IFERROR(IF(INDEX(Pedidos_DB!C:C,3+MATCH($D$2,Pedidos_DB!C4:C110,0)+23)<>$D$2,"",INDEX(Pedidos_DB!B:B,3+MATCH($D$2,Pedidos_DB!C4:C110,0)+23)),"") | C33: =IFERROR(IF(INDEX(Pedidos_DB!C:C,3+MATCH($D$2,Pedidos_DB!C4:C110,0)+23)<>$D$2,"",INDEX(Pedidos_DB!C:C,3+MATCH($D$2,Pedidos_DB!C4:C110,0)+23)),"") | D33: =IFERROR(IF(INDEX(Pedidos_DB!C:C,3+MATCH($D$2,Pedidos_DB!C4:C110,0)+23)<>$D$2,"",INDEX(Pedidos_DB!D:D,3+MATCH($D$2,Pedidos_DB!C4:C110,0)+23)),"") | E33: =IFERROR(IF(INDEX(Pedidos_DB!C:C,3+MATCH($D$2,Pedidos_DB!C4:C110,0)+23)<>$D$2,"",INDEX(Pedidos_DB!E:E,3+MATCH($D$2,Pedidos_DB!C4:C110,0)+23)),"") | F33: =IFERROR(IF(INDEX(Pedidos_DB!C:C,3+MATCH($D$2,Pedidos_DB!C4:C110,0)+23)<>$D$2,"",INDEX(Pedidos_DB!F:F,3+MATCH($D$2,Pedidos_DB!C4:C110,0)+23)),"") | G33: =IFERROR(IF(INDEX(Pedidos_DB!C:C,3+MATCH($D$2,Pedidos_DB!C4:C110,0)+23)<>$D$2,"",INDEX(Pedidos_DB!G:G,3+MATCH($D$2,Pedidos_DB!C4:C110,0)+23)),"") | H33: =IFERROR(IF(INDEX(Pedidos_DB!C:C,3+MATCH($D$2,Pedidos_DB!C4:C110,0)+23)<>$D$2,"",INDEX(Pedidos_DB!H:H,3+MATCH($D$2,Pedidos_DB!C4:C110,0)+23)),"")
B34: =IFERROR(IF(INDEX(Pedidos_DB!C:C,3+MATCH($D$2,Pedidos_DB!C4:C110,0)+24)<>$D$2,"",INDEX(Pedidos_DB!B:B,3+MATCH($D$2,Pedidos_DB!C4:C110,0)+24)),"") | C34: =IFERROR(IF(INDEX(Pedidos_DB!C:C,3+MATCH($D$2,Pedidos_DB!C4:C110,0)+24)<>$D$2,"",INDEX(Pedidos_DB!C:C,3+MATCH($D$2,Pedidos_DB!C4:C110,0)+24)),"") | D34: =IFERROR(IF(INDEX(Pedidos_DB!C:C,3+MATCH($D$2,Pedidos_DB!C4:C110,0)+24)<>$D$2,"",INDEX(Pedidos_DB!D:D,3+MATCH($D$2,Pedidos_DB!C4:C110,0)+24)),"") | E34: =IFERROR(IF(INDEX(Pedidos_DB!C:C,3+MATCH($D$2,Pedidos_DB!C4:C110,0)+24)<>$D$2,"",INDEX(Pedidos_DB!E:E,3+MATCH($D$2,Pedidos_DB!C4:C110,0)+24)),"") | F34: =IFERROR(IF(INDEX(Pedidos_DB!C:C,3+MATCH($D$2,Pedidos_DB!C4:C110,0)+24)<>$D$2,"",INDEX(Pedidos_DB!F:F,3+MATCH($D$2,Pedidos_DB!C4:C110,0)+24)),"") | G34: =IFERROR(IF(INDEX(Pedidos_DB!C:C,3+MATCH($D$2,Pedidos_DB!C4:C110,0)+24)<>$D$2,"",INDEX(Pedidos_DB!G:G,3+MATCH($D$2,Pedidos_DB!C4:C110,0)+24)),"") | H34: =IFERROR(IF(INDEX(Pedidos_DB!C:C,3+MATCH($D$2,Pedidos_DB!C4:C110,0)+24)<>$D$2,"",INDEX(Pedidos_DB!H:H,3+MATCH($D$2,Pedidos_DB!C4:C110,0)+24)),"")

Sheet Despesas
B1: 💸 CONTROLE DE DESPESAS
B2: 📅 Filtro de Mês: | D2: Outubro | G2: ⬅ Selecione o mês para atualizar
B4: 💸 Total Despesas | E4: 🧾 Nº Compras | H4: 📦 Maior Compra | J4: 📊 Média
B5: =SUMIF(Despesas_DB!C4:C99,$D$2,Despesas_DB!H4:H99) -> 3890 | E5: =COUNTIF(Despesas_DB!C4:C99,$D$2) -> 17 | H5: =IFERROR(_xludf.maxifs(Despesas_DB!H4:H99,Despesas_DB!C4:C99,$D$2),0) -> 0 | J5: =IFERROR(B5/D5,0) -> 0
B8: 📋 Compras do Mês Selecionado | I8: 📊 Por Categoria
B9: Data | C9: Descrição | D9: Produto | E9: Custo Unit. | F9: Qtd | G9: Total (R$) | I9: Categoria | J9: Total (R$) | K9: %
B10: =IFERROR(IF(INDEX(Despesas_DB!C:C,3+MATCH($D$2,Despesas_DB!C4:C99,0)+0)<>$D$2,"",INDEX(Despesas_DB!B:B,3+MATCH($D$2,Despesas_DB!C4:C99,0)+0)),"") -> 2024-10-01 | C10: =IFERROR(IF(INDEX(Despesas_DB!C:C,3+MATCH($D$2,Despesas_DB!C4:C99,0)+0)<>$D$2,"",INDEX(Despesas_DB!D:D,3+MATCH($D$2,Despesas_DB!C4:C99,0)+0)),"") -> Compra de Óleo | D10: =IFERROR(IF(INDEX(Despesas_DB!C:C,3+MATCH($D$2,Despesas_DB!C4:C99,0)+0)<>$D$2,"",INDEX(Despesas_DB!E:E,3+MATCH($D$2,Despesas_DB!C4:C99,0)+0)),"") -> Óleo de Rícino | E10: =IFERROR(IF(INDEX(Despesas_DB!C:C,3+MATCH($D$2,Despesas_DB!C4:C99,0)+0)<>$D$2,"",INDEX(Despesas_DB!F:F,3+MATCH($D$2,Despesas_DB!C4:C99,0)+0)),"") -> 12 | F10: =IFERROR(IF(INDEX(Despesas_DB!C:C,3+MATCH($D$2,Despesas_DB!C4:C99,0)+0)<>$D$2,"",INDEX(Despesas_DB!G:G,3+MATCH($D$2,Despesas_DB!C4:C99,0)+0)),"") -> 30 | G10: =IFERROR(IF(INDEX(Despesas_DB!C:C,3+MATCH($D$2,Despesas_DB!C4:C99,0)+0)<>$D$2,"",INDEX(Despesas_DB!H:H,3+MATCH($D$2,Despesas_DB!C4:C99,0)+0)),"") -> 360 | I10: Shampoo | J10: =SUMPRODUCT((Despesas_DB!C4:C99=$D$2)*(ISNUMBER(SEARCH(I10,Despesas_DB!E4:E99))*Despesas_DB!H4:H99)) -> 720 | K10: =IFERROR(J10/B5,0) -> 0.18508997
B11: =IFERROR(IF(INDEX(Despesas_DB!C:C,3+MATCH($D$2,Despesas_DB!C4:C99,0)+1)<>$D$2,"",INDEX(Despesas_DB!B:B,3+MATCH($D$2,Despesas_DB!C4:C99,0)+1)),"") -> 2024-10-02 | C11: =IFERROR(IF(INDEX(Despesas_DB!C:C,3+MATCH($D$2,Despesas_DB!C4:C99,0)+1)<>$D$2,"",INDEX(Despesas_DB!D:D,3+MATCH($D$2,Despesas_DB!C4:C99,0)+1)),"") -> Compra de Creme de Pentear | D11: =IFERROR(IF(INDEX(Despesas_DB!C:C,3+MATCH($D$2,Despesas_DB!C4:C99,0)+1)<>$D$2,"",INDEX(Despesas_DB!E:E,3+MATCH($D$2,Despesas_DB!C4:C99,0)+1)),"") -> Creme de Pentear Antifrizz | E11: =IFERROR(IF(INDEX(Despesas_DB!C:C,3+MATCH($D$2,Despesas_DB!C4:C99,0)+1)<>$D$2,"",INDEX(Despesas_DB!F:F,3+MATCH($D$2,Despesas_DB!C4:C99,0)+1)),"") -> 10 | F11: =IFERROR(IF(INDEX(Despesas_DB!C:C,3+MATCH($D$2,Despesas_DB!C4:C99,0)+1)<>$D$2,"",INDEX(Despesas_DB!G:G,3+MATCH($D$2,Despesas_DB!C4:C99,0)+1)),"") -> 20 | G11: =IFERROR(IF(INDEX(Despesas_DB!C:C,3+MATCH($D$2,Despesas_DB!C4:C99,0)+1)<>$D$2,"",INDEX(Despesas_DB!H:H,3+MATCH($D$2,Despesas_DB!C4:C99,0)+1)),"") -> 200 | I11: Condicionador | J11: =SUMPRODUCT((Despesas_DB!C4:C99=$D$2)*(ISNUMBER(SEARCH(I11,Despesas_DB!E4:E99))*Despesas_DB!H4:H99)) -> 670 | K11: =IFERROR(J11/B5,0) -> 0.1722365
B12: =IFERROR(IF(INDEX(Despesas_DB!C:C,3+MATCH($D$2,Despesas_DB!C4:C99,0)+2)<>$D$2,"",INDEX(Despesas_DB!B:B,3+MATCH($D$2,Despesas_DB!C4:C99,0)+2)),"") -> 2024-10-03 | C12: =IFERROR(IF(INDEX(Despesas_DB!C:C,3+MATCH($D$2,Despesas_DB!C4:C99,0)+2)<>$D$2,"",INDEX(Despesas_DB!D:D,3+MATCH($D$2,Despesas_DB!C4:C99,0)+2)),"") -> Compra de Creme de Pentear | D12: =IFERROR(IF(INDEX(Despesas_DB!C:C,3+MATCH($D$2,Despesas_DB!C4:C99,0)+2)<>$D$2,"",INDEX(Despesas_DB!E:E,3+MATCH($D$2,Despesas_DB!C4:C99,0)+2)),"") -> Creme de Pentear Hidratante | E12: =IFERROR(IF(INDEX(Despesas_DB!C:C,3+MATCH($D$2,Despesas_DB!C4:C99,0)+2)<>$D$2,"",INDEX(Despesas_DB!F:F,3+MATCH($D$2,Despesas_DB!C4:C99,0)+2)),"") -> 13 | F12: =IFERROR(IF(INDEX(Despesas_DB!C:C,3+MATCH($D$2,Despesas_DB!C4:C99,0)+2)<>$D$2,"",INDEX(Despesas_DB!G:G,3+MATCH($D$2,Despesas_DB!C4:C99,0)+2)),"") -> 10 | G12: =IFERROR(IF(INDEX(Despesas_DB!C:C,3+MATCH($D$2,Despesas_DB!C4:C99,0)+2)<>$D$2,"",INDEX(Despesas_DB!H:H,3+MATCH($D$2,Despesas_DB!C4:C99,0)+2)),"") -> 130 | I12: Ampola | J12: =SUMPRODUCT((Despesas_DB!C4:C99=$D$2)*(ISNUMBER(SEARCH(I12,Despesas_DB!E4:E99))*Despesas_DB!H4:H99)) -> 60 | K12: =IFERROR(J12/B5,0) -> 0.015424165
B13: =IFERROR(IF(INDEX(Despesas_DB!C:C,3+MATCH($D$2,Despesas_DB!C4:C99,0)+3)<>$D$2,"",INDEX(Despesas_DB!B:B,3+MATCH($D$2,Despesas_DB!C4:C99,0)+3)),"") -> 2024-10-05 | C13: =IFERROR(IF(INDEX(Despesas_DB!C:C,3+MATCH($D$2,Despesas_DB!C4:C99,0)+3)<>$D$2,"",INDEX(Despesas_DB!D:D,3+MATCH($D$2,Despesas_DB!C4:C99,0)+3)),"") -> Compra de Shampoo | D13: =IFERROR(IF(INDEX(Despesas_DB!C:C,3+MATCH($D$2,Despesas_DB!C4:C99,0)+3)<>$D$2,"",INDEX(Despesas_DB!E:E,3+MATCH($D$2,Despesas_DB!C4:C99,0)+3)),"") -> Shampoo Detox | E13: =IFERROR(IF(INDEX(Despesas_DB!C:C,3+MATCH($D$2,Despesas_DB!C4:C99,0)+3)<>$D$2,"",INDEX(Despesas_DB!F:F,3+MATCH($D$2,Despesas_DB!C4:C99,0)+3)),"") -> 14 | F13: =IFERROR(IF(INDEX(Despesas_DB!C:C,3+MATCH($D$2,Despesas_DB!C4:C99,0)+3)<>$D$2,"",INDEX(Despesas_DB!G:G,3+MATCH($D$2,Despesas_DB!C4:C99,0)+3)),"") -> 20 | G13: =IFERROR(IF(INDEX(Despesas_DB!C:C,3+MATCH($D$2,Despesas_DB!C4:C99,0)+3)<>$D$2,"",INDEX(Despesas_DB!H:H,3+MATCH($D$2,Despesas_DB!C4:C99,0)+3)),"") -> 280 | I13: Máscara | J13: =SUMPRODUCT((Despesas_DB!C4:C99=$D$2)*(ISNUMBER(SEARCH(I13,Despesas_DB!E4:E99))*Despesas_DB!H4:H99)) -> 300 | K13: =IFERROR(J13/B5,0) -> 0.077120823
B14: =IFERROR(IF(INDEX(Despesas_DB!C:C,3+MATCH($D$2,Despesas_DB!C4:C99,0)+4)<>$D$2,"",INDEX(Despesas_DB!B:B,3+MATCH($D$2,Despesas_DB!C4:C99,0)+4)),"") -> 2024-10-06 | C14: =IFERROR(IF(INDEX(Despesas_DB!C:C,3+MATCH($D$2,Despesas_DB!C4:C99,0)+4)<>$D$2,"",INDEX(Despesas_DB!D:D,3+MATCH($D$2,Despesas_DB!C4:C99,0)+4)),"") -> Compra de Shampoo | D14: =IFERROR(IF(INDEX(Despesas_DB!C:C,3+MATCH($D$2,Despesas_DB!C4:C99,0)+4)<>$D$2,"",INDEX(Despesas_DB!E:E,3+MATCH($D$2,Despesas_DB!C4:C99,0)+4)),"") -> Shampoo Antirresíduos | E14: =IFERROR(IF(INDEX(Despesas_DB!C:C,3+MATCH($D$2,Despesas_DB!C4:C99,0)+4)<>$D$2,"",INDEX(Despesas_DB!F:F,3+MATCH($D$2,Despesas_DB!C4:C99,0)+4)),"") -> 17 | F14: =IFERROR(IF(INDEX(Despesas_DB!C:C,3+MATCH($D$2,Despesas_DB!C4:C99,0)+4)<>$D$2,"",INDEX(Despesas_DB!G:G,3+MATCH($D$2,Despesas_DB!C4:C99,0)+4)),"") -> 10 | G14: =IFERROR(IF(INDEX(Despesas_DB!C:C,3+MATCH($D$2,Despesas_DB!C4:C99,0)+4)<>$D$2,"",INDEX(Despesas_DB!H:H,3+MATCH($D$2,Despesas_DB!C4:C99,0)+4)),"") -> 170 | I14: Óleo | J14: =SUMPRODUCT((Despesas_DB!C4:C99=$D$2)*(ISNUMBER(SEARCH(I14,Despesas_DB!E4:E99))*Despesas_DB!H4:H99)) -> 1150 | K14: =IFERROR(J14/B5,0) -> 0.29562982
B15: =IFERROR(IF(INDEX(Despesas_DB!C:C,3+MATCH($D$2,Despesas_DB!C4:C99,0)+5)<>$D$2,"",INDEX(Despesas_DB!B:B,3+MATCH($D$2,Despesas_DB!C4:C99,0)+5)),"") -> 2024-10-07 | C15: =IFERROR(IF(INDEX(Despesas_DB!C:C,3+MATCH($D$2,Despesas_DB!C4:C99,0)+5)<>$D$2,"",INDEX(Despesas_DB!D:D,3+MATCH($D$2,Despesas_DB!C4:C99,0)+5)),"") -> Compra de Shampoo | D15: =IFERROR(IF(INDEX(Despesas_DB!C:C,3+MATCH($D$2,Despesas_DB!C4:C99,0)+5)<>$D$2,"",INDEX(Despesas_DB!E:E,3+MATCH($D$2,Despesas_DB!C4:C99,0)+5)),"") -> Shampoo Reparador | E15: =IFERROR(IF(INDEX(Despesas_DB!C:C,3+MATCH($D$2,Despesas_DB!C4:C99,0)+5)<>$D$2,"",INDEX(Despesas_DB!F:F,3+MATCH($D$2,Despesas_DB!C4:C99,0)+5)),"") -> 18 | F15: =IFERROR(IF(INDEX(Despesas_DB!C:C,3+MATCH($D$2,Despesas_DB!C4:C99,0)+5)<>$D$2,"",INDEX(Despesas_DB!G:G,3+MATCH($D$2,Despesas_DB!C4:C99,0)+5)),"") -> 15 | G15: =IFERROR(IF(INDEX(Despesas_DB!C:C,3+MATCH($D$2,Despesas_DB!C4:C99,0)+5)<>$D$2,"",INDEX(Despesas_DB!H:H,3+MATCH($D$2,Despesas_DB!C4:C99,0)+5)),"") -> 270 | I15: Leave-in | J15: =SUMPRODUCT((Despesas_DB!C4:C99=$D$2)*(ISNUMBER(SEARCH(I15,Despesas_DB!E4:E99))*Despesas_DB!H4:H99)) -> 560 | K15: =IFERROR(J15/B5,0) -> 0.14395887
B16: =IFERROR(IF(INDEX(Despesas_DB!C:C,3+MATCH($D$2,Despesas_DB!C4:C99,0)+6)<>$D$2,"",INDEX(Despesas_DB!B:B,3+MATCH($D$2,Despesas_DB!C4:C99,0)+6)),"") -> 2024-10-08 | C16: =IFERROR(IF(INDEX(Despesas_DB!C:C,3+MATCH($D$2,Despesas_DB!C4:C99,0)+6)<>$D$2,"",INDEX(Despesas_DB!D:D,3+MATCH($D$2,Despesas_DB!C4:C99,0)+6)),"") -> Compra de Condicionador | D16: =IFERROR(IF(INDEX(Despesas_DB!C:C,3+MATCH($D$2,Despesas_DB!C4:C99,0)+6)<>$D$2,"",INDEX(Despesas_DB!E:E,3+MATCH($D$2,Despesas_DB!C4:C99,0)+6)),"") -> Condicionador Revitalizante | E16: =IFERROR(IF(INDEX(Despesas_DB!C:C,3+MATCH($D$2,Despesas_DB!C4:C99,0)+6)<>$D$2,"",INDEX(Despesas_DB!F:F,3+MATCH($D$2,Despesas_DB!C4:C99,0)+6)),"") -> 17 | F16: =IFERROR(IF(INDEX(Despesas_DB!C:C,3+MATCH($D$2,Despesas_DB!C4:C99,0)+6)<>$D$2,"",INDEX(Despesas_DB!G:G,3+MATCH($D$2,Despesas_DB!C4:C99,0)+6)),"") -> 15 | G16: =IFERROR(IF(INDEX(Despesas_DB!C:C,3+MATCH($D$2,Despesas_DB!C4:C99,0)+6)<>$D$2,"",INDEX(Despesas_DB!H:H,3+MATCH($D$2,Despesas_DB!C4:C99,0)+6)),"") -> 255 | I16: Creme de Pentear | J16: =SUMPRODUCT((Despesas_DB!C4:C99=$D$2)*(ISNUMBER(SEARCH(I16,Despesas_DB!E4:E99))*Despesas_DB!H4:H99)) -> 430 | K16: =IFERROR(J16/B5,0) -> 0.11053985
B17: =IFERROR(IF(INDEX(Despesas_DB!C:C,3+MATCH($D$2,Despesas_DB!C4:C99,0)+7)<>$D$2,"",INDEX(Despesas_DB!B:B,3+MATCH($D$2,Despesas_DB!C4:C99,0)+7)),"") -> 2024-10-09 | C17: =IFERROR(IF(INDEX(Despesas_DB!C:C,3+MATCH($D$2,Despesas_DB!C4:C99,0)+7)<>$D$2,"",INDEX(Despesas_DB!D:D,3+MATCH($D$2,Despesas_DB!C4:C99,0)+7)),"") -> Compra de Condicionador | D17: =IFERROR(IF(INDEX(Despesas_DB!C:C,3+MATCH($D$2,Despesas_DB!C4:C99,0)+7)<>$D$2,"",INDEX(Despesas_DB!E:E,3+MATCH($D$2,Despesas_DB!C4:C99,0)+7)),"") -> Condicionador Nutritivo | E17: =IFERROR(IF(INDEX(Despesas_DB!C:C,3+MATCH($D$2,Despesas_DB!C4:C99,0)+7)<>$D$2,"",INDEX(Despesas_DB!F:F,3+MATCH($D$2,Despesas_DB!C4:C99,0)+7)),"") -> 15 | F17: =IFERROR(IF(INDEX(Despesas_DB!C:C,3+MATCH($D$2,Despesas_DB!C4:C99,0)+7)<>$D$2,"",INDEX(Despesas_DB!G:G,3+MATCH($D$2,Despesas_DB!C4:C99,0)+7)),"") -> 15 | G17: =IFERROR(IF(INDEX(Despesas_DB!C:C,3+MATCH($D$2,Despesas_DB!C4:C99,0)+7)<>$D$2,"",INDEX(Despesas_DB!H:H,3+MATCH($D$2,Despesas_DB!C4:C99,0)+7)),"") -> 225
B18: =IFERROR(IF(INDEX(Despesas_DB!C:C,3+MATCH($D$2,Despesas_DB!C4:C99,0)+8)<>$D$2,"",INDEX(Despesas_DB!B:B,3+MATCH($D$2,Despesas_DB!C4:C99,0)+8)),"") -> 2024-10-10 | C18: =IFERROR(IF(INDEX(Despesas_DB!C:C,3+MATCH($D$2,Despesas_DB!C4:C99,0)+8)<>$D$2,"",INDEX(Despesas_DB!D:D,3+MATCH($D$2,Despesas_DB!C4:C99,0)+8)),"") -> Compra de Máscara | D18: =IFERROR(IF(INDEX(Despesas_DB!C:C,3+MATCH($D$2,Despesas_DB!C4:C99,0)+8)<>$D$2,"",INDEX(Despesas_DB!E:E,3+MATCH($D$2,Despesas_DB!C4:C99,0)+8)),"") -> Máscara de Reconstrução | E18: =IFERROR(IF(INDEX(Despesas_DB!C:C,3+MATCH($D$2,Despesas_DB!C4:C99,0)+8)<>$D$2,"",INDEX(Despesas_DB!F:F,3+MATCH($D$2,Despesas_DB!C4:C99,0)+8)),"") -> 30 | F18: =IFERROR(IF(INDEX(Despesas_DB!C:C,3+MATCH($D$2,Despesas_DB!C4:C99,0)+8)<>$D$2,"",INDEX(Despesas_DB!G:G,3+MATCH($D$2,Despesas_DB!C4:C99,0)+8)),"") -> 10 | G18: =IFERROR(IF(INDEX(Despesas_DB!C:C,3+MATCH($D$2,Despesas_DB!C4:C99,0)+8)<>$D$2,"",INDEX(Despesas_DB!H:H,3+MATCH($D$2,Despesas_DB!C4:C99,0)+8)),"") -> 300
B19: =IFERROR(IF(INDEX(Despesas_DB!C:C,3+MATCH($D$2,Despesas_DB!C4:C99,0)+9)<>$D$2,"",INDEX(Despesas_DB!B:B,3+MATCH($D$2,Despesas_DB!C4:C99,0)+9)),"") -> 2024-10-11 | C19: =IFERROR(IF(INDEX(Despesas_DB!C:C,3+MATCH($D$2,Despesas_DB!C4:C99,0)+9)<>$D$2,"",INDEX(Despesas_DB!D:D,3+MATCH($D$2,Despesas_DB!C4:C99,0)+9)),"") -> Compra de Condicionador | D19: =IFERROR(IF(INDEX(Despesas_DB!C:C,3+MATCH($D$2,Despesas_DB!C4:C99,0)+9)<>$D$2,"",INDEX(Despesas_DB!E:E,3+MATCH($D$2,Despesas_DB!C4:C99,0)+9)),"") -> Condicionador Antifrizz | E19: =IFERROR(IF(INDEX(Despesas_DB!C:C,3+MATCH($D$2,Despesas_DB!C4:C99,0)+9)<>$D$2,"",INDEX(Despesas_DB!F:F,3+MATCH($D$2,Despesas_DB!C4:C99,0)+9)),"") -> 19 | F19: =IFERROR(IF(INDEX(Despesas_DB!C:C,3+MATCH($D$2,Despesas_DB!C4:C99,0)+9)<>$D$2,"",INDEX(Despesas_DB!G:G,3+MATCH($D$2,Despesas_DB!C4:C99,0)+9)),"") -> 10 | G19: =IFERROR(IF(INDEX(Despesas_DB!C:C,3+MATCH($D$2,Despesas_DB!C4:C99,0)+9)<>$D$2,"",INDEX(Despesas_DB!H:H,3+MATCH($D$2,Despesas_DB!C4:C99,0)+9)),"") -> 190
B20: =IFERROR(IF(INDEX(Despesas_DB!C:C,3+MATCH($D$2,Despesas_DB!C4:C99,0)+10)<>$D$2,"",INDEX(Despesas_DB!B:B,3+MATCH($D$2,Despesas_DB!C4:C99,0)+10)),"") -> 2024-10-13 | C20: =IFERROR(IF(INDEX(Despesas_DB!C:C,3+MATCH($D$2,Despesas_DB!C4:C99,0)+10)<>$D$2,"",INDEX(Despesas_DB!D:D,3+MATCH($D$2,Despesas_DB!C4:C99,0)+10)),"") -> Compra de Óleo | D20: =IFERROR(IF(INDEX(Despesas_DB!C:C,3+MATCH($D$2,Despesas_DB!C4:C99,0)+10)<>$D$2,"",INDEX(Despesas_DB!E:E,3+MATCH($D$2,Despesas_DB!C4:C99,0)+10)),"") -> Óleo de Jojoba | E20: =IFERROR(IF(INDEX(Despesas_DB!C:C,3+MATCH($D$2,Despesas_DB!C4:C99,0)+10)<>$D$2,"",INDEX(Despesas_DB!F:F,3+MATCH($D$2,Despesas_DB!C4:C99,0)+10)),"") -> 17 | F20: =IFERROR(IF(INDEX(Despesas_DB!C:C,3+MATCH($D$2,Despesas_DB!C4:C99,0)+10)<>$D$2,"",INDEX(Despesas_DB!G:G,3+MATCH($D$2,Despesas_DB!C4:C99,0)+10)),"") -> 20 | G20: =IFERROR(IF(INDEX(Despesas_DB!C:C,3+MATCH($D$2,Despesas_DB!C4:C99,0)+10)<>$D$2,"",INDEX(Despesas_DB!H:H,3+MATCH($D$2,Despesas_DB!C4:C99,0)+10)),"") -> 340
B21: =IFERROR(IF(INDEX(Despesas_DB!C:C,3+MATCH($D$2,Despesas_DB!C4:C99,0)+11)<>$D$2,"",INDEX(Despesas_DB!B:B,3+MATCH($D$2,Despesas_DB!C4:C99,0)+11)),"") -> 2024-10-14 | C21: =IFERROR(IF(INDEX(Despesas_DB!C:C,3+MATCH($D$2,Despesas_DB!C4:C99,0)+11)<>$D$2,"",INDEX(Despesas_DB!D:D,3+MATCH($D$2,Despesas_DB!C4:C99,0)+11)),"") -> Compra de Leave-in | D21: =IFERROR(IF(INDEX(Despesas_DB!C:C,3+MATCH($D$2,Despesas_DB!C4:C99,0)+11)<>$D$2,"",INDEX(Despesas_DB!E:E,3+MATCH($D$2,Despesas_DB!C4:C99,0)+11)),"") -> Leave-in Nutritivo | E21: =IFERROR(IF(INDEX(Despesas_DB!C:C,3+MATCH($D$2,Despesas_DB!C4:C99,0)+11)<>$D$2,"",INDEX(Despesas_DB!F:F,3+MATCH($D$2,Despesas_DB!C4:C99,0)+11)),"") -> 14 | F21: =IFERROR(IF(INDEX(Despesas_DB!C:C,3+MATCH($D$2,Despesas_DB!C4:C99,0)+11)<>$D$2,"",INDEX(Despesas_DB!G:G,3+MATCH($D$2,Despesas_DB!C4:C99,0)+11)),"") -> 10 | G21: =IFERROR(IF(INDEX(Despesas_DB!C:C,3+MATCH($D$2,Despesas_DB!C4:C99,0)+11)<>$D$2,"",INDEX(Despesas_DB!H:H,3+MATCH($D$2,Despesas_DB!C4:C99,0)+11)),"") -> 140
B22: =IFERROR(IF(INDEX(Despesas_DB!C:C,3+MATCH($D$2,Despesas_DB!C4:C99,0)+12)<>$D$2,"",INDEX(Despesas_DB!B:B,3+MATCH($D$2,Despesas_DB!C4:C99,0)+12)),"") -> 2024-10-15 | C22: =IFERROR(IF(INDEX(Despesas_DB!C:C,3+MATCH($D$2,Despesas_DB!C4:C99,0)+12)<>$D$2,"",INDEX(Despesas_DB!D:D,3+MATCH($D$2,Despesas_DB!C4:C99,0)+12)),"") -> Compra de Leave-in | D22: =IFERROR(IF(INDEX(Despesas_DB!C:C,3+MATCH($D$2,Despesas_DB!C4:C99,0)+12)<>$D$2,"",INDEX(Despesas_DB!E:E,3+MATCH($D$2,Despesas_DB!C4:C99,0)+12)),"") -> Leave-in para Cabelos Cacheados | E22: =IFERROR(IF(INDEX(Despesas_DB!C:C,3+MATCH($D$2,Despesas_DB!C4:C99,0)+12)<>$D$2,"",INDEX(Despesas_DB!F:F,3+MATCH($D$2,Despesas_DB!C4:C99,0)+12)),"") -> 16 | F22: =IFERROR(IF(INDEX(Despesas_DB!C:C,3+MATCH($D$2,Despesas_DB!C4:C99,0)+12)<>$D$2,"",INDEX(Despesas_DB!G:G,3+MATCH($D$2,Despesas_DB!C4:C99,0)+12)),"") -> 15 | G22: =IFERROR(IF(INDEX(Despesas_DB!C:C,3+MATCH($D$2,Despesas_DB!C4:C99,0)+12)<>$D$2,"",INDEX(Despesas_DB!H:H,3+MATCH($D$2,Despesas_DB!C4:C99,0)+12)),"") -> 240
B23: =IFERROR(IF(INDEX(Despesas_DB!C:C,3+MATCH($D$2,Despesas_DB!C4:C99,0)+13)<>$D$2,"",INDEX(Despesas_DB!B:B,3+MATCH($D$2,Despesas_DB!C4:C99,0)+13)),"") -> 2024-10-16 | C23: =IFERROR(IF(INDEX(Despesas_DB!C:C,3+MATCH($D$2,Despesas_DB!C4:C99,0)+13)<>$D$2,"",INDEX(Despesas_DB!D:D,3+MATCH($D$2,Despesas_DB!C4:C99,0)+13)),"") -> Compra de Leave-in | D23: =IFERROR(IF(INDEX(Despesas_DB!C:C,3+MATCH($D$2,Despesas_DB!C4:C99,0)+13)<>$D$2,"",INDEX(Despesas_DB!E:E,3+MATCH($D$2,Despesas_DB!C4:C99,0)+13)),"") -> Leave-in Hidratante | E23: =IFERROR(IF(INDEX(Despesas_DB!C:C,3+MATCH($D$2,Despesas_DB!C4:C99,0)+13)<>$D$2,"",INDEX(Despesas_DB!F:F,3+MATCH($D$2,Despesas_DB!C4:C99,0)+13)),"") -> 12 | F23: =IFERROR(IF(INDEX(Despesas_DB!C:C,3+MATCH($D$2,Despesas_DB!C4:C99,0)+13)<>$D$2,"",INDEX(Despesas_DB!G:G,3+MATCH($D$2,Despesas_DB!C4:C99,0)+13)),"") -> 15 | G23: =IFERROR(IF(INDEX(Despesas_DB!C:C,3+MATCH($D$2,Despesas_DB!C4:C99,0)+13)<>$D$2,"",INDEX(Despesas_DB!H:H,3+MATCH($D$2,Despesas_DB!C4:C99,0)+13)),"") -> 180
B24: =IFERROR(IF(INDEX(Despesas_DB!C:C,3+MATCH($D$2,Despesas_DB!C4:C99,0)+14)<>$D$2,"",INDEX(Despesas_DB!B:B,3+MATCH($D$2,Despesas_DB!C4:C99,0)+14)),"") -> 2024-10-17 | C24: =IFERROR(IF(INDEX(Despesas_DB!C:C,3+MATCH($D$2,Despesas_DB!C4:C99,0)+14)<>$D$2,"",INDEX(Despesas_DB!D:D,3+MATCH($D$2,Despesas_DB!C4:C99,0)+14)),"") -> Compra de Creme de Pentear | D24: =IFERROR(IF(INDEX(Despesas_DB!C:C,3+MATCH($D$2,Despesas_DB!C4:C99,0)+14)<>$D$2,"",INDEX(Despesas_DB!E:E,3+MATCH($D$2,Despesas_DB!C4:C99,0)+14)),"") -> Creme de Pentear Modelador de Cachos | E24: =IFERROR(IF(INDEX(Despesas_DB!C:C,3+MATCH($D$2,Despesas_DB!C4:C99,0)+14)<>$D$2,"",INDEX(Despesas_DB!F:F,3+MATCH($D$2,Despesas_DB!C4:C99,0)+14)),"") -> 10 | F24: =IFERROR(IF(INDEX(Despesas_DB!C:C,3+MATCH($D$2,Despesas_DB!C4:C99,0)+14)<>$D$2,"",INDEX(Despesas_DB!G:G,3+MATCH($D$2,Despesas_DB!C4:C99,0)+14)),"") -> 10 | G24: =IFERROR(IF(INDEX(Despesas_DB!C:C,3+MATCH($D$2,Despesas_DB!C4:C99,0)+14)<>$D$2,"",INDEX(Despesas_DB!H:H,3+MATCH($D$2,Despesas_DB!C4:C99,0)+14)),"") -> 100
B25: =IFERROR(IF(INDEX(Despesas_DB!C:C,3+MATCH($D$2,Despesas_DB!C4:C99,0)+15)<>$D$2,"",INDEX(Despesas_DB!B:B,3+MATCH($D$2,Despesas_DB!C4:C99,0)+15)),"") -> 2024-10-18 | C25: =IFERROR(IF(INDEX(Despesas_DB!C:C,3+MATCH($D$2,Despesas_DB!C4:C99,0)+15)<>$D$2,"",INDEX(Despesas_DB!D:D,3+MATCH($D$2,Despesas_DB!C4:C99,0)+15)),"") -> Compra de Óleo | D25: =IFERROR(IF(INDEX(Despesas_DB!C:C,3+MATCH($D$2,Despesas_DB!C4:C99,0)+15)<>$D$2,"",INDEX(Despesas_DB!E:E,3+MATCH($D$2,Despesas_DB!C4:C99,0)+15)),"") -> Óleo de Argan | E25: =IFERROR(IF(INDEX(Despesas_DB!C:C,3+MATCH($D$2,Despesas_DB!C4:C99,0)+15)<>$D$2,"",INDEX(Despesas_DB!F:F,3+MATCH($D$2,Despesas_DB!C4:C99,0)+15)),"") -> 15 | F25: =IFERROR(IF(INDEX(Despesas_DB!C:C,3+MATCH($D$2,Despesas_DB!C4:C99,0)+15)<>$D$2,"",INDEX(Despesas_DB!G:G,3+MATCH($D$2,Despesas_DB!C4:C99,0)+15)),"") -> 30 | G25: =IFERROR(IF(INDEX(Despesas_DB!C:C,3+MATCH($D$2,Despesas_DB!C4:C99,0)+15)<>$D$2,"",INDEX(Despesas_DB!H:H,3+MATCH($D$2,Despesas_DB!C4:C99,0)+15)),"") -> 450
B26: =IFERROR(IF(INDEX(Despesas_DB!C:C,3+MATCH($D$2,Despesas_DB!C4:C99,0)+16)<>$D$2,"",INDEX(Despesas_DB!B:B,3+MATCH($D$2,Despesas_DB!C4:C99,0)+16)),"") -> 2024-10-20 | C26: =IFERROR(IF(INDEX(Despesas_DB!C:C,3+MATCH($D$2,Despesas_DB!C4:C99,0)+16)<>$D$2,"",INDEX(Despesas_DB!D:D,3+MATCH($D$2,Despesas_DB!C4:C99,0)+16)),"") -> Compra de Ampola | D26: =IFERROR(IF(INDEX(Despesas_DB!C:C,3+MATCH($D$2,Despesas_DB!C4:C99,0)+16)<>$D$2,"",INDEX(Despesas_DB!E:E,3+MATCH($D$2,Despesas_DB!C4:C99,0)+16)),"") -> Ampola de Fortalecimento | E26: =IFERROR(IF(INDEX(Despesas_DB!C:C,3+MATCH($D$2,Despesas_DB!C4:C99,0)+16)<>$D$2,"",INDEX(Despesas_DB!F:F,3+MATCH($D$2,Despesas_DB!C4:C99,0)+16)),"") -> 6 | F26: =IFERROR(IF(INDEX(Despesas_DB!C:C,3+MATCH($D$2,Despesas_DB!C4:C99,0)+16)<>$D$2,"",INDEX(Despesas_DB!G:G,3+MATCH($D$2,Despesas_DB!C4:C99,0)+16)),"") -> 10 | G26: =IFERROR(IF(INDEX(Despesas_DB!C:C,3+MATCH($D$2,Despesas_DB!C4:C99,0)+16)<>$D$2,"",INDEX(Despesas_DB!H:H,3+MATCH($D$2,Despesas_DB!C4:C99,0)+16)),"") -> 60
B27: =IFERROR(IF(INDEX(Despesas_DB!C:C,3+MATCH($D$2,Despesas_DB!C4:C99,0)+17)<>$D$2,"",INDEX(Despesas_DB!B:B,3+MATCH($D$2,Despesas_DB!C4:C99,0)+17)),"") | C27: =IFERROR(IF(INDEX(Despesas_DB!C:C,3+MATCH($D$2,Despesas_DB!C4:C99,0)+17)<>$D$2,"",INDEX(Despesas_DB!D:D,3+MATCH($D$2,Despesas_DB!C4:C99,0)+17)),"") | D27: =IFERROR(IF(INDEX(Despesas_DB!C:C,3+MATCH($D$2,Despesas_DB!C4:C99,0)+17)<>$D$2,"",INDEX(Despesas_DB!E:E,3+MATCH($D$2,Despesas_DB!C4:C99,0)+17)),"") | E27: =IFERROR(IF(INDEX(Despesas_DB!C:C,3+MATCH($D$2,Despesas_DB!C4:C99,0)+17)<>$D$2,"",INDEX(Despesas_DB!F:F,3+MATCH($D$2,Despesas_DB!C4:C99,0)+17)),"") | F27: =IFERROR(IF(INDEX(Despesas_DB!C:C,3+MATCH($D$2,Despesas_DB!C4:C99,0)+17)<>$D$2,"",INDEX(Despesas_DB!G:G,3+MATCH($D$2,Despesas_DB!C4:C99,0)+17)),"") | G27: =IFERROR(IF(INDEX(Despesas_DB!C:C,3+MATCH($D$2,Despesas_DB!C4:C99,0)+17)<>$D$2,"",INDEX(Despesas_DB!H:H,3+MATCH($D$2,Despesas_DB!C4:C99,0)+17)),"")
B28: =IFERROR(IF(INDEX(Despesas_DB!C:C,3+MATCH($D$2,Despesas_DB!C4:C99,0)+18)<>$D$2,"",INDEX(Despesas_DB!B:B,3+MATCH($D$2,Despesas_DB!C4:C99,0)+18)),"") | C28: =IFERROR(IF(INDEX(Despesas_DB!C:C,3+MATCH($D$2,Despesas_DB!C4:C99,0)+18)<>$D$2,"",INDEX(Despesas_DB!D:D,3+MATCH($D$2,Despesas_DB!C4:C99,0)+18)),"") | D28: =IFERROR(IF(INDEX(Despesas_DB!C:C,3+MATCH($D$2,Despesas_DB!C4:C99,0)+18)<>$D$2,"",INDEX(Despesas_DB!E:E,3+MATCH($D$2,Despesas_DB!C4:C99,0)+18)),"") | E28: =IFERROR(IF(INDEX(Despesas_DB!C:C,3+MATCH($D$2,Despesas_DB!C4:C99,0)+18)<>$D$2,"",INDEX(Despesas_DB!F:F,3+MATCH($D$2,Despesas_DB!C4:C99,0)+18)),"") | F28: =IFERROR(IF(INDEX(Despesas_DB!C:C,3+MATCH($D$2,Despesas_DB!C4:C99,0)+18)<>$D$2,"",INDEX(Despesas_DB!G:G,3+MATCH($D$2,Despesas_DB!C4:C99,0)+18)),"") | G28: =IFERROR(IF(INDEX(Despesas_DB!C:C,3+MATCH($D$2,Despesas_DB!C4:C99,0)+18)<>$D$2,"",INDEX(Despesas_DB!H:H,3+MATCH($D$2,Despesas_DB!C4:C99,0)+18)),"")
B29: =IFERROR(IF(INDEX(Despesas_DB!C:C,3+MATCH($D$2,Despesas_DB!C4:C99,0)+19)<>$D$2,"",INDEX(Despesas_DB!B:B,3+MATCH($D$2,Despesas_DB!C4:C99,0)+19)),"") | C29: =IFERROR(IF(INDEX(Despesas_DB!C:C,3+MATCH($D$2,Despesas_DB!C4:C99,0)+19)<>$D$2,"",INDEX(Despesas_DB!D:D,3+MATCH($D$2,Despesas_DB!C4:C99,0)+19)),"") | D29: =IFERROR(IF(INDEX(Despesas_DB!C:C,3+MATCH($D$2,Despesas_DB!C4:C99,0)+19)<>$D$2,"",INDEX(Despesas_DB!E:E,3+MATCH($D$2,Despesas_DB!C4:C99,0)+19)),"") | E29: =IFERROR(IF(INDEX(Despesas_DB!C:C,3+MATCH($D$2,Despesas_DB!C4:C99,0)+19)<>$D$2,"",INDEX(Despesas_DB!F:F,3+MATCH($D$2,Despesas_DB!C4:C99,0)+19)),"") | F29: =IFERROR(IF(INDEX(Despesas_DB!C:C,3+MATCH($D$2,Despesas_DB!C4:C99,0)+19)<>$D$2,"",INDEX(Despesas_DB!G:G,3+MATCH($D$2,Despesas_DB!C4:C99,0)+19)),"") | G29: =IFERROR(IF(INDEX(Despesas_DB!C:C,3+MATCH($D$2,Despesas_DB!C4:C99,0)+19)<>$D$2,"",INDEX(Despesas_DB!H:H,3+MATCH($D$2,Despesas_DB!C4:C99,0)+19)),"")

Sheet Lucro
B1: 📈 ANÁLISE DE LUCRO
B2: 📅 Filtro de Mês: | D2: Outubro | G2: ⬅ Selecione o mês para atualizar
B4: 💰 Faturamento | C4: 💸 Custo Total | E4: 📈 Lucro | F4: 📊 Margem | G4: 💡 Rentab.
B5: =SUMIF(Pedidos_DB!C4:C110,$D$2,Pedidos_DB!G4:G110) -> 8328.2 | C5: =SUMIF(Despesas_DB!C4:C99,$D$2,Despesas_DB!H4:H99) -> 3890 | E5: =B5-C5 -> 4438.2 | F5: =IFERROR(E5/B5,0) -> 0.53291227 | G5: =IFERROR(E5/C5,0) -> 1.1409254
B8: 🏆 Lucro por Produto
B9: Produto | C9: Qtd Vendida | D9: Faturamento | E9: Custo | F9: Lucro | G9: Margem
B10: Shampoo Antiqueda | C10: =SUMPRODUCT((Pedidos_DB!C4:C110=$D$2)*(Pedidos_DB!E4:E110=B10)*Pedidos_DB!F4:F110) -> 20 | D10: =SUMPRODUCT((Pedidos_DB!C4:C110=$D$2)*(Pedidos_DB!E4:E110=B10)*Pedidos_DB!G4:G110) -> 378 | E10: =SUMIFS(Despesas_DB!H4:H99,Despesas_DB!C4:C99,$D$2,Despesas_DB!E4:E99,B10) -> 0 | F10: =D10-E10 -> 378 | G10: =IFERROR(F10/D10,0) -> 1
B11: Condicionador Nutritivo | C11: =SUMPRODUCT((Pedidos_DB!C4:C110=$D$2)*(Pedidos_DB!E4:E110=B11)*Pedidos_DB!F4:F110) -> 22 | D11: =SUMPRODUCT((Pedidos_DB!C4:C110=$D$2)*(Pedidos_DB!E4:E110=B11)*Pedidos_DB!G4:G110) -> 426.8 | E11: =SUMIFS(Despesas_DB!H4:H99,Despesas_DB!C4:C99,$D$2,Despesas_DB!E4:E99,B11) -> 225 | F11: =D11-E11 -> 201.8 | G11: =IFERROR(F11/D11,0) -> 0.47282099
B12: Ampola de Reparação | C12: =SUMPRODUCT((Pedidos_DB!C4:C110=$D$2)*(Pedidos_DB!E4:E110=B12)*Pedidos_DB!F4:F110) -> 5 | D12: =SUMPRODUCT((Pedidos_DB!C4:C110=$D$2)*(Pedidos_DB!E4:E110=B12)*Pedidos_DB!G4:G110) -> 62.5 | E12: =SUMIFS(Despesas_DB!H4:H99,Despesas_DB!C4:C99,$D$2,Despesas_DB!E4:E99,B12) -> 0 | F12: =D12-E12 -> 62.5 | G12: =IFERROR(F12/D12,0) -> 1
B13: Máscara de Hidratação | C13: =SUMPRODUCT((Pedidos_DB!C4:C110=$D$2)*(Pedidos_DB!E4:E110=B13)*Pedidos_DB!F4:F110) -> 15 | D13: =SUMPRODUCT((Pedidos_DB!C4:C110=$D$2)*(Pedidos_DB!E4:E110=B13)*Pedidos_DB!G4:G110) -> 525 | E13: =SUMIFS(Despesas_DB!H4:H99,Despesas_DB!C4:C99,$D$2,Despesas_DB!E4:E99,B13) -> 0 | F13: =D13-E13 -> 525 | G13: =IFERROR(F13/D13,0) -> 1
B14: Óleo de Rícino | C14: =SUMPRODUCT((Pedidos_DB!C4:C110=$D$2)*(Pedidos_DB!E4:E110=B14)*Pedidos_DB!F4:F110) -> 20 | D14: =SUMPRODUCT((Pedidos_DB!C4:C110=$D$2)*(Pedidos_DB!E4:E110=B14)*Pedidos_DB!G4:G110) -> 400 | E14: =SUMIFS(Despesas_DB!H4:H99,Despesas_DB!C4:C99,$D$2,Despesas_DB!E4:E99,B14) -> 360 | F14: =D14-E14 -> 40 | G14: =IFERROR(F14/D14,0) -> 0.1
B15: Creme de Pentear Hidratante | C15: =SUMPRODUCT((Pedidos_DB!C4:C110=$D$2)*(Pedidos_DB!E4:E110=B15)*Pedidos_DB!F4:F110) -> 10 | D15: =SUMPRODUCT((Pedidos_DB!C4:C110=$D$2)*(Pedidos_DB!E4:E110=B15)*Pedidos_DB!G4:G110) -> 182 | E15: =SUMIFS(Despesas_DB!H4:H99,Despesas_DB!C4:C99,$D$2,Despesas_DB!E4:E99,B15) -> 130 | F15: =D15-E15 -> 52 | G15: =IFERROR(F15/D15,0) -> 0.28571429
B16: Shampoo Detox | C16: =SUMPRODUCT((Pedidos_DB!C4:C110=$D$2)*(Pedidos_DB!E4:E110=B16)*Pedidos_DB!F4:F110) -> 15 | D16: =SUMPRODUCT((Pedidos_DB!C4:C110=$D$2)*(Pedidos_DB!E4:E110=B16)*Pedidos_DB!G4:G110) -> 298.5 | E16: =SUMIFS(Despesas_DB!H4:H99,Despesas_DB!C4:C99,$D$2,Despesas_DB!E4:E99,B16) -> 280 | F16: =D16-E16 -> 18.5 | G16: =IFERROR(F16/D16,0) -> 0.061976549
B17: Máscara de Nutrição Profunda | C17: =SUMPRODUCT((Pedidos_DB!C4:C110=$D$2)*(Pedidos_DB!E4:E110=B17)*Pedidos_DB!F4:F110) -> 30 | D17: =SUMPRODUCT((Pedidos_DB!C4:C110=$D$2)*(Pedidos_DB!E4:E110=B17)*Pedidos_DB!G4:G110) -> 1260 | E17: =SUMIFS(Despesas_DB!H4:H99,Despesas_DB!C4:C99,$D$2,Despesas_DB!E4:E99,B17) -> 0 | F17: =D17-E17 -> 1260 | G17: =IFERROR(F17/D17,0) -> 1
B18: Leave-in Nutritivo | C18: =SUMPRODUCT((Pedidos_DB!C4:C110=$D$2)*(Pedidos_DB!E4:E110=B18)*Pedidos_DB!F4:F110) -> 0 | D18: =SUMPRODUCT((Pedidos_DB!C4:C110=$D$2)*(Pedidos_DB!E4:E110=B18)*Pedidos_DB!G4:G110) -> 0 | E18: =SUMIFS(Despesas_DB!H4:H99,Despesas_DB!C4:C99,$D$2,Despesas_DB!E4:E99,B18) -> 140 | F18: =D18-E18 -> -140 | G18: =IFERROR(F18/D18,0) -> 0
B19: Condicionador Antifrizz | C19: =SUMPRODUCT((Pedidos_DB!C4:C110=$D$2)*(Pedidos_DB!E4:E110=B19)*Pedidos_DB!F4:F110) -> 10 | D19: =SUMPRODUCT((Pedidos_DB!C4:C110=$D$2)*(Pedidos_DB!E4:E110=B19)*Pedidos_DB!G4:G110) -> 271 | E19: =SUMIFS(Despesas_DB!H4:H99,Despesas_DB!C4:C99,$D$2,Despesas_DB!E4:E99,B19) -> 190 | F19: =D19-E19 -> 81 | G19: =IFERROR(F19/D19,0) -> 0.29889299
B20: Óleo de Argan | C20: =SUMPRODUCT((Pedidos_DB!C4:C110=$D$2)*(Pedidos_DB!E4:E110=B20)*Pedidos_DB!F4:F110) -> 8 | D20: =SUMPRODUCT((Pedidos_DB!C4:C110=$D$2)*(Pedidos_DB!E4:E110=B20)*Pedidos_DB!G4:G110) -> 239.2 | E20: =SUMIFS(Despesas_DB!H4:H99,Despesas_DB!C4:C99,$D$2,Despesas_DB!E4:E99,B20) -> 450 | F20: =D20-E20 -> -210.8 | G20: =IFERROR(F20/D20,0) -> -0.8812709
B21: Máscara Reconstrutora | C21: =SUMPRODUCT((Pedidos_DB!C4:C110=$D$2)*(Pedidos_DB!E4:E110=B21)*Pedidos_DB!F4:F110) -> 12 | D21: =SUMPRODUCT((Pedidos_DB!C4:C110=$D$2)*(Pedidos_DB!E4:E110=B21)*Pedidos_DB!G4:G110) -> 480 | E21: =SUMIFS(Despesas_DB!H4:H99,Despesas_DB!C4:C99,$D$2,Despesas_DB!E4:E99,B21) -> 0 | F21: =D21-E21 -> 480 | G21: =IFERROR(F21/D21,0) -> 1
B22: Creme de Pentear Antifrizz | C22: =SUMPRODUCT((Pedidos_DB!C4:C110=$D$2)*(Pedidos_DB!E4:E110=B22)*Pedidos_DB!F4:F110) -> 25 | D22: =SUMPRODUCT((Pedidos_DB!C4:C110=$D$2)*(Pedidos_DB!E4:E110=B22)*Pedidos_DB!G4:G110) -> 375 | E22: =SUMIFS(Despesas_DB!H4:H99,Despesas_DB!C4:C99,$D$2,Despesas_DB!E4:E99,B22) -> 200 | F22: =D22-E22 -> 175 | G22: =IFERROR(F22/D22,0) -> 0.46666667
B23: Shampoo Antirresíduos | C23: =SUMPRODUCT((Pedidos_DB!C4:C110=$D$2)*(Pedidos_DB!E4:E110=B23)*Pedidos_DB!F4:F110) -> 10 | D23: =SUMPRODUCT((Pedidos_DB!C4:C110=$D$2)*(Pedidos_DB!E4:E110=B23)*Pedidos_DB!G4:G110) -> 235 | E23: =SUMIFS(Despesas_DB!H4:H99,Despesas_DB!C4:C99,$D$2,Despesas_DB!E4:E99,B23) -> 170 | F23: =D23-E23 -> 65 | G23: =IFERROR(F23/D23,0) -> 0.27659574
B24: Shampoo Reparador | C24: =SUMPRODUCT((Pedidos_DB!C4:C110=$D$2)*(Pedidos_DB!E4:E110=B24)*Pedidos_DB!F4:F110) -> 18 | D24: =SUMPRODUCT((Pedidos_DB!C4:C110=$D$2)*(Pedidos_DB!E4:E110=B24)*Pedidos_DB!G4:G110) -> 450 | E24: =SUMIFS(Despesas_DB!H4:H99,Despesas_DB!C4:C99,$D$2,Despesas_DB!E4:E99,B24) -> 270 | F24: =D24-E24 -> 180 | G24: =IFERROR(F24/D24,0) -> 0.4
B25: Condicionador Revitalizante | C25: =SUMPRODUCT((Pedidos_DB!C4:C110=$D$2)*(Pedidos_DB!E4:E110=B25)*Pedidos_DB!F4:F110) -> 20 | D25: =SUMPRODUCT((Pedidos_DB!C4:C110=$D$2)*(Pedidos_DB!E4:E110=B25)*Pedidos_DB!G4:G110) -> 438 | E25: =SUMIFS(Despesas_DB!H4:H99,Despesas_DB!C4:C99,$D$2,Despesas_DB!E4:E99,B25) -> 255 | F25: =D25-E25 -> 183 | G25: =IFERROR(F25/D25,0) -> 0.41780822
B26: Condicionador Hidratante | C26: =SUMPRODUCT((Pedidos_DB!C4:C110=$D$2)*(Pedidos_DB!E4:E110=B26)*Pedidos_DB!F4:F110) -> 22 | D26: =SUMPRODUCT((Pedidos_DB!C4:C110=$D$2)*(Pedidos_DB!E4:E110=B26)*Pedidos_DB!G4:G110) -> 360.8 | E26: =SUMIFS(Despesas_DB!H4:H99,Despesas_DB!C4:C99,$D$2,Despesas_DB!E4:E99,B26) -> 0 | F26: =D26-E26 -> 360.8 | G26: =IFERROR(F26/D26,0) -> 1
B27: Óleo de Jojoba | C27: =SUMPRODUCT((Pedidos_DB!C4:C110=$D$2)*(Pedidos_DB!E4:E110=B27)*Pedidos_DB!F4:F110) -> 15 | D27: =SUMPRODUCT((Pedidos_DB!C4:C110=$D$2)*(Pedidos_DB!E4:E110=B27)*Pedidos_DB!G4:G110) -> 523.5 | E27: =SUMIFS(Despesas_DB!H4:H99,Despesas_DB!C4:C99,$D$2,Despesas_DB!E4:E99,B27) -> 340 | F27: =D27-E27 -> 183.5 | G27: =IFERROR(F27/D27,0) -> 0.35052531
B28: Ampola de Fortalecimento | C28: =SUMPRODUCT((Pedidos_DB!C4:C110=$D$2)*(Pedidos_DB!E4:E110=B28)*Pedidos_DB!F4:F110) -> 18 | D28: =SUMPRODUCT((Pedidos_DB!C4:C110=$D$2)*(Pedidos_DB!E4:E110=B28)*Pedidos_DB!G4:G110) -> 230.4 | E28: =SUMIFS(Despesas_DB!H4:H99,Despesas_DB!C4:C99,$D$2,Despesas_DB!E4:E99,B28) -> 60 | F28: =D28-E28 -> 170.4 | G28: =IFERROR(F28/D28,0) -> 0.73958333
B29: Máscara Reparadora de Pontas | C29: =SUMPRODUCT((Pedidos_DB!C4:C110=$D$2)*(Pedidos_DB!E4:E110=B29)*Pedidos_DB!F4:F110) -> 5 | D29: =SUMPRODUCT((Pedidos_DB!C4:C110=$D$2)*(Pedidos_DB!E4:E110=B29)*Pedidos_DB!G4:G110) -> 192.5 | E29: =SUMIFS(Despesas_DB!H4:H99,Despesas_DB!C4:C99,$D$2,Despesas_DB!E4:E99,B29) -> 0 | F29: =D29-E29 -> 192.5 | G29: =IFERROR(F29/D29,0) -> 1
B30: Máscara de Reconstrução | C30: =SUMPRODUCT((Pedidos_DB!C4:C110=$D$2)*(Pedidos_DB!E4:E110=B30)*Pedidos_DB!F4:F110) -> 20 | D30: =SUMPRODUCT((Pedidos_DB!C4:C110=$D$2)*(Pedidos_DB!E4:E110=B30)*Pedidos_DB!G4:G110) -> 1000 | E30: =SUMIFS(Despesas_DB!H4:H99,Despesas_DB!C4:C99,$D$2,Despesas_DB!E4:E99,B30) -> 300 | F30: =D30-E30 -> 700 | G30: =IFERROR(F30/D30,0) -> 0.7
B31: Shampoo Hidratante | C31: =SUMPRODUCT((Pedidos_DB!C4:C110=$D$2)*(Pedidos_DB!E4:E110=B31)*Pedidos_DB!F4:F110) -> 0 | D31: =SUMPRODUCT((Pedidos_DB!C4:C110=$D$2)*(Pedidos_DB!E4:E110=B31)*Pedidos_DB!G4:G110) -> 0 | E31: =SUMIFS(Despesas_DB!H4:H99,Despesas_DB!C4:C99,$D$2,Despesas_DB!E4:E99,B31) -> 0 | F31: =D31-E31 -> 0 | G31: =IFERROR(F31/D31,0) -> 0
B32: Creme de Pentear Modelador de Cachos | C32: =SUMPRODUCT((Pedidos_DB!C4:C110=$D$2)*(Pedidos_DB!E4:E110=B32)*Pedidos_DB!F4:F110) -> 0 | D32: =SUMPRODUCT((Pedidos_DB!C4:C110=$D$2)*(Pedidos_DB!E4:E110=B32)*Pedidos_DB!G4:G110) -> 0 | E32: =SUMIFS(Despesas_DB!H4:H99,Despesas_DB!C4:C99,$D$2,Despesas_DB!E4:E99,B32) -> 100 | F32: =D32-E32 -> -100 | G32: =IFERROR(F32/D32,0) -> 0
B33: Leave-in Hidratante | C33: =SUMPRODUCT((Pedidos_DB!C4:C110=$D$2)*(Pedidos_DB!E4:E110=B33)*Pedidos_DB!F4:F110) -> 0 | D33: =SUMPRODUCT((Pedidos_DB!C4:C110=$D$2)*(Pedidos_DB!E4:E110=B33)*Pedidos_DB!G4:G110) -> 0 | E33: =SUMIFS(Despesas_DB!H4:H99,Despesas_DB!C4:C99,$D$2,Despesas_DB!E4:E99,B33) -> 180 | F33: =D33-E33 -> -180 | G33: =IFERROR(F33/D33,0) -> 0
B34: Ampola de Reconstrução | C34: =SUMPRODUCT((Pedidos_DB!C4:C110=$D$2)*(Pedidos_DB!E4:E110=B34)*Pedidos_DB!F4:F110) -> 0 | D34: =SUMPRODUCT((Pedidos_DB!C4:C110=$D$2)*(Pedidos_DB!E4:E110=B34)*Pedidos_DB!G4:G110) -> 0 | E34: =SUMIFS(Despesas_DB!H4:H99,Despesas_DB!C4:C99,$D$2,Despesas_DB!E4:E99,B34) -> 0 | F34: =D34-E34 -> 0 | G34: =IFERROR(F34/D34,0) -> 0

Sheet Estoque
B1: 📦 CONTROLE DE ESTOQUE
B3: 📦 Total SKUs | E3: 📈 Alta | H3: 📉 Baixa | K3: 💰 Valor Total
B4: =57 -> 57 | E4: =COUNTIF(H9:H65,"Alta") -> 44 | H4: =COUNTIF(H9:H65,"Baixa") -> 2 | K4: =SUMPRODUCT(F9:F65*E9:E65) -> 37494
B7: 📋 Catálogo Completo de Estoque | J7: 📊 Resumo por Categoria
B8: Categoria | C8: Produto | D8: Qtd. Inicial | E8: Custo Unit. | F8: Qtd. Atual | G8: Variação | H8: Status | J8: Categoria | K8: Qtd Atual | L8: Valor Estoque
B9: Shampoo | C9: Shampoo Antiqueda | D9: 50 | E9: 18.9 | F9: 30 | G9: =F9-D9 -> -20 | H9: =IF(F9>=D9,"Alta",IF(F9>=D9*0.5,"Normal","Baixa")) -> Normal | J9: Shampoo | K9: =SUMIF(B9:B65,J9,F9:F65) -> 222 | L9: =SUMPRODUCT((B9:B65=J9)*F9:F65*E9:E65) -> 4636.5
B10: Shampoo | C10: Shampoo Detox | D10: 30 | E10: 19.9 | F10: 35 | G10: =F10-D10 -> 5 | H10: =IF(F10>=D10,"Alta",IF(F10>=D10*0.5,"Normal","Baixa")) -> Alta | J10: Condicionador | K10: =SUMIF(B9:B65,J10,F9:F65) -> 189 | L10: =SUMPRODUCT((B9:B65=J10)*F9:F65*E9:E65) -> 3832.8
B11: Shampoo | C11: Shampoo Antirresíduos | D11: 45 | E11: 23.5 | F11: 45 | G11: =F11-D11 -> 0 | H11: =IF(F11>=D11,"Alta",IF(F11>=D11*0.5,"Normal","Baixa")) -> Alta | J11: Ampola | K11: =SUMIF(B9:B65,J11,F9:F65) -> 272 | L11: =SUMPRODUCT((B9:B65=J11)*F9:F65*E9:E65) -> 3576.6
B12: Shampoo | C12: Shampoo Reparador | D12: 35 | E12: 25 | F12: 32 | G12: =F12-D12 -> -3 | H12: =IF(F12>=D12,"Alta",IF(F12>=D12*0.5,"Normal","Baixa")) -> Normal | J12: Máscara | K12: =SUMIF(B9:B65,J12,F9:F65) -> 218 | L12: =SUMPRODUCT((B9:B65=J12)*F9:F65*E9:E65) -> 8298.5
B13: Shampoo | C13: Shampoo Hidratante | D13: 25 | E13: 15.5 | F13: 25 | G13: =F13-D13 -> 0 | H13: =IF(F13>=D13,"Alta",IF(F13>=D13*0.5,"Normal","Baixa")) -> Alta | J13: Óleo | K13: =SUMIF(B9:B65,J13,F9:F65) -> 242 | L13: =SUMPRODUCT((B9:B65=J13)*F9:F65*E9:E65) -> 6885.3
B14: Shampoo | C14: Shampoo Revitalizante | D14: 20 | E14: 17.9 | F14: 20 | G14: =F14-D14 -> 0 | H14: =IF(F14>=D14,"Alta",IF(F14>=D14*0.5,"Normal","Baixa")) -> Alta | J14: Leave-in | K14: =SUMIF(B9:B65,J14,F9:F65) -> 275 | L14: =SUMPRODUCT((B9:B65=J14)*F9:F65*E9:E65) -> 6211
B15: Shampoo | C15: Shampoo Anti-frizz | D15: 15 | E15: 22 | F15: 15 | G15: =F15-D15 -> 0 | H15: =IF(F15>=D15,"Alta",IF(F15>=D15*0.5,"Normal","Baixa")) -> Alta | J15: Creme de Pentear | K15: =SUMIF(B9:B65,J15,F9:F65) -> 227 | L15: =SUMPRODUCT((B9:B65=J15)*F9:F65*E9:E65) -> 4053.3
B16: Shampoo | C16: Shampoo para Cabelos Cacheados | D16: 20 | E16: 22 | F16: 20 | G16: =F16-D16 -> 0 | H16: =IF(F16>=D16,"Alta",IF(F16>=D16*0.5,"Normal","Baixa")) -> Alta
B17: Condicionador | C17: Condicionador Nutritivo | D17: 70 | E17: 18.6 | F17: 56 | G17: =F17-D17 -> -14 | H17: =IF(F17>=D17,"Alta",IF(F17>=D17*0.5,"Normal","Baixa")) -> Normal
B18: Condicionador | C18: Condicionador Revitalizante | D18: 40 | E18: 21.9 | F18: 35 | G18: =F18-D18 -> -5 | H18: =IF(F18>=D18,"Alta",IF(F18>=D18*0.5,"Normal","Baixa")) -> Normal
B19: Condicionador | C19: Condicionador Hidratante | D19: 50 | E19: 16.4 | F19: 28 | G19: =F19-D19 -> -22 | H19: =IF(F19>=D19,"Alta",IF(F19>=D19*0.5,"Normal","Baixa")) -> Normal
B20: Condicionador | C20: Condicionador Antifrizz | D20: 20 | E20: 27.1 | F20: 20 | G20: =F20-D20 -> 0 | H20: =IF(F20>=D20,"Alta",IF(F20>=D20*0.5,"Normal","Baixa")) -> Alta
B21: Condicionador | C21: Condicionador Reestruturante | D21: 15 | E21: 20 | F21: 15 | G21: =F21-D21 -> 0 | H21: =IF(F21>=D21,"Alta",IF(F21>=D21*0.5,"Normal","Baixa")) -> Alta
B22: Condicionador | C22: Condicionador de Cabelos Cacheados | D22: 15 | E22: 24.5 | F22: 15 | G22: =F22-D22 -> 0 | H22: =IF(F22>=D22,"Alta",IF(F22>=D22*0.5,"Normal","Baixa")) -> Alta
B23: Condicionador | C23: Condicionador Reconstrutor | D23: 20 | E23: 17.8 | F23: 20 | G23: =F23-D23 -> 0 | H23: =IF(F23>=D23,"Alta",IF(F23>=D23*0.5,"Normal","Baixa")) -> Alta
B24: Ampola | C24: Ampola de Reparação | D24: 50 | E24: 12.5 | F24: 45 | G24: =F24-D24 -> -5 | H24: =IF(F24>=D24,"Alta",IF(F24>=D24*0.5,"Normal","Baixa")) -> Normal
B25: Ampola | C25: Ampola de Reconstrução | D25: 30 | E25: 15 | F25: 30 | G25: =F25-D25 -> 0 | H25: =IF(F25>=D25,"Alta",IF(F25>=D25*0.5,"Normal","Baixa")) -> Alta
B26: Ampola | C26: Ampola de Fortalecimento | D26: 60 | E26: 12.8 | F26: 52 | G26: =F26-D26 -> -8 | H26: =IF(F26>=D26,"Alta",IF(F26>=D26*0.5,"Normal","Baixa")) -> Normal
B27: Ampola | C27: Ampola de Brilho | D27: 30 | E27: 11.9 | F27: 30 | G27: =F27-D27 -> 0 | H27: =IF(F27>=D27,"Alta",IF(F27>=D27*0.5,"Normal","Baixa")) -> Alta
... B65: Creme de Pentear | C65: Creme de Pentear Anti-frizz | D65: 20 | E65: 19.1 | F65: 20 | G65: =F65-D65 -> 0 | H65: =IF(F65>=D65,"Alta",IF(F65>=D65*0.5,"Normal","Baixa")) -> Alta

Sheet Pedidos_DB
B1: 🛒 BASE DE DADOS — PEDIDOS
B2: Preencha: Data, Mês (texto), Salão, Produto, Qtd, Valor, Status.
B3: Data | C3: Mês | D3: Cliente/Salão | E3: Produto | F3: Qtd | G3: Valor (R$) | H3: Status | I3: Dt. Entrega
B4: 2024-09-03 | C4: Setembro | D4: Salão Glamour | E4: Shampoo Antiqueda | F4: 15 | G4: 283.5 | H4: concluído | I4: 2024-09-08
B5: 2024-09-05 | C5: Setembro | D5: Salão Cabelos de Ouro | E5: Condicionador Nutritivo | F5: 20 | G5: 356 | H5: concluído | I5: 2024-09-09
B6: 2024-09-08 | C6: Setembro | D6: Salão Beleza & Cia | E6: Ampola de Reparação | F6: 10 | G6: 125 | H6: concluído | I6: 2024-09-12
B7: 2024-09-10 | C7: Setembro | D7: Salão Bella Cabelos | E7: Máscara de Hidratação | F7: 12 | G7: 420 | H7: concluído | I7: 2024-09-14
B8: 2024-09-12 | C8: Setembro | D8: Salão Luxo Capilar | E8: Óleo de Rícino | F8: 18 | G8: 360 | H8: concluído | I8: 2024-09-16
B9: 2024-09-15 | C9: Setembro | D9: Salão Glamour | E9: Creme de Pentear Hidratante | F9: 15 | G9: 273 | H9: concluído | I9: 2024-09-19
B10: 2024-09-17 | C10: Setembro | D10: Salão Cabelos de Ouro | E10: Shampoo Detox | F10: 20 | G10: 398 | H10: concluído | I10: 2024-09-21
B11: 2024-09-20 | C11: Setembro | D11: Salão Beleza & Cia | E11: Máscara de Nutrição Profunda | F11: 10 | G11: 420 | H11: concluído | I11: 2024-09-24
B12: 2024-09-22 | C12: Setembro | D12: Salão Bella Cabelos | E12: Leave-in Nutritivo | F12: 15 | G12: 351 | H12: concluído | I12: 2024-09-26
B13: 2024-09-25 | C13: Setembro | D13: Salão Luxo Capilar | E13: Condicionador Antifrizz | F13: 12 | G13: 325.2 | H13: concluído | I13: 2024-09-29
B14: 2024-09-27 | C14: Setembro | D14: Salão Glamour | E14: Óleo de Argan | F14: 8 | G14: 239.2 | H14: concluído | I14: 2024-10-01
B15: 2024-10-10 | C15: Outubro | D15: Salão Beleza & Cia | E15: Shampoo Antiqueda | F15: 20 | G15: 378 | H15: concluído | I15: 2024-10-15
B16: 2024-10-10 | C16: Outubro | D16: Salão Glamour | E16: Condicionador Nutritivo | F16: 10 | G16: 194 | H16: concluído | I16: 2024-10-12
B17: 2024-10-11 | C17: Outubro | D17: Salão Luxo Capilar | E17: Ampola de Reparação | F17: 5 | G17: 62.5 | H17: pendente
B18: 2024-10-12 | C18: Outubro | D18: Salão Cabelos de Ouro | E18: Máscara de Hidratação | F18: 15 | G18: 525 | H18: concluído | I18: 2024-10-14
B19: 2024-10-13 | C19: Outubro | D19: Salão Beleza & Cia | E19: Máscara Reconstrutora | F19: 12 | G19: 480 | H19: concluído | I19: 2024-10-18
B20: 2024-10-14 | C20: Outubro | D20: Salão Bella Cabelos | E20: Óleo de Argan | F20: 8 | G20: 239.2 | H20: concluído | I20: 2024-10-16
B21: 2024-10-15 | C21: Outubro | D21: Salão Glamour | E21: Óleo de Rícino | F21: 20 | G21: 400 | H21: concluído | I21: 2024-10-17
B22: 2024-10-16 | C22: Outubro | D22: Salão Cabelos de Ouro | E22: Creme de Pentear Antifrizz | F22: 25 | G22: 375 | H22: concluído | I22: 2024-10-22
B23: 2024-10-16 | C23: Outubro | D23: Salão Luxo Capilar | E23: Creme de Pentear Hidratante | F23: 10 | G23: 182 | H23: concluído | I23: 2024-10-20
B24: 2024-10-17 | C24: Outubro | D24: Salão Cabelos de Ouro | E24: Shampoo Detox | F24: 15 | G24: 298.5 | H24: processo
B25: 2024-10-18 | C25: Outubro | D25: Salão Beleza & Cia | E25: Shampoo Antirresíduos | F25: 10 | G25: 235 | H25: pendente | I25: 2024-10-21
B26: 2024-10-18 | C26: Outubro | D26: Salão Luxo Capilar | E26: Shampoo Reparador | F26: 18 | G26: 450 | H26: pendente | I26: 2024-10-20
B27: 2024-10-19 | C27: Outubro | D27: Salão Cabelos de Ouro | E27: Condicionador Revitalizante | F27: 20 | G27: 438 | H27: pendente
B28: 2024-10-20 | C28: Outubro | D28: Salão Bella Cabelos | E28: Condicionador Nutritivo | F28: 12 | G28: 232.8 | H28: concluído | I28: 2024-10-24
B29: 2024-10-21 | C29: Outubro | D29: Salão Glamour | E29: Condicionador Hidratante | F29: 22 | G29: 360.8 | H29: concluído | I29: 2024-10-26
B30: 2024-10-21 | C30: Outubro | D30: Salão Luxo Capilar | E30: Condicionador Antifrizz | F30: 10 | G30: 271 | H30: concluído | I30: 2024-10-23
B31: 2024-10-22 | C31: Outubro | D31: Salão Cabelos de Ouro | E31: Óleo de Jojoba | F31: 15 | G31: 523.5 | H31: concluído | I31: 2024-10-25
B32: 2024-10-23 | C32: Outubro | D32: Salão Cabelos de Ouro | E32: Ampola de Fortalecimento | F32: 18 | G32: 230.4 | H32: pendente
B33: 2024-10-24 | C33: Outubro | D33: Salão Bella Cabelos | E33: Máscara Reparadora de Pontas | F33: 5 | G33: 192.5 | H33: concluído | I33: 2024-10-28
B34: 2024-10-25 | C34: Outubro | D34: Salão Glamour | E34: Máscara de Nutrição Profunda | F34: 30 | G34: 1260 | H34: concluído | I34: 2024-10-27
B35: 2024-10-26 | C35: Outubro | D35: Salão Cabelos de Ouro | E35: Máscara de Reconstrução | F35: 20 | G35: 1000 | H35: processo
B36: 2024-11-02 | C36: Novembro | D36: Salão Cabelos de Ouro | E36: Shampoo Hidratante | F36: 15 | G36: 232.5 | H36: concluído | I36: 2024-11-07
B37: 2024-11-03 | C37: Novembro | D37: Salão Glamour | E37: Leave-in Nutritivo | F37: 20 | G37: 468 | H37: concluído | I37: 2024-11-06
B38: 2024-11-04 | C38: Novembro | D38: Salão Bella Cabelos | E38: Ampola de Fortalecimento | F38: 10 | G38: 128 | H38: concluído | I38: 2024-11-08
B39: 2024-11-05 | C39: Novembro | D39: Salão Luxo Capilar | E39: Máscara de Hidratação | F39: 18 | G39: 630 | H39: concluído | I39: 2024-11-09
B40: 2024-11-06 | C40: Novembro | D40: Salão Beleza & Cia | E40: Óleo de Argan | F40: 12 | G40: 358.8 | H40: concluído | I40: 2024-11-11
B41: 2024-11-07 | C41: Novembro | D41: Salão Cabelos de Ouro | E41: Condicionador Antifrizz | F41: 15 | G41: 406.5 | H41: pendente
B42: 2024-11-08 | C42: Novembro | D42: Salão Glamour | E42: Creme de Pentear Modelador de Cachos | F42: 25 | G42: 410 | H42: concluído | I42: 2024-11-12
B43: 2024-11-10 | C43: Novembro | D43: Salão Bella Cabelos | E43: Shampoo Reparador | F43: 10 | G43: 250 | H43: processo
B44: 2024-11-11 | C44: Novembro | D44: Salão Luxo Capilar | E44: Máscara de Nutrição Profunda | F44: 20 | G44: 840 | H44: concluído | I44: 2024-11-15
B45: 2024-11-12 | C45: Novembro | D45: Salão Beleza & Cia | E45: Leave-in Hidratante | F45: 30 | G45: 597 | H45: concluído | I45: 2024-11-16
B46: 2024-11-13 | C46: Novembro | D46: Salão Cabelos de Ouro | E46: Ampola de Reconstrução | F46: 12 | G46: 180 | H46: concluído | I46: 2024-11-17
B47: 2024-11-14 | C47: Novembro | D47: Salão Glamour | E47: Shampoo Antirresíduos | F47: 20 | G47: 470 | H47: pendente
B48: 2024-11-15 | C48: Novembro | D48: Salão Bella Cabelos | E48: Máscara Reconstrutora | F48: 8 | G48: 320 | H48: concluído | I48: 2024-11-19
B49: 2024-11-17 | C49: Novembro | D49: Salão Luxo Capilar | E49: Condicionador Revitalizante | F49: 25 | G49: 547.5 | H49: concluído | I49: 2024-11-21
B50: 2024-11-18 | C50: Novembro | D50: Salão Cabelos de Ouro | E50: Óleo de Jojoba | F50: 10 | G50: 349 | H50: concluído | I50: 2024-11-22

Sheet Despesas_DB
B1: 💸 BASE DE DADOS — DESPESAS
B2: Preencha: Data, Mês (texto), Descrição, Produto, Custo Unit., Qtd. Total é automático.
B3: Data | C3: Mês | D3: Descrição | E3: Produto | F3: Custo Unit. | G3: Qtd | H3: Total (auto)
B4: 2024-09-02 | C4: Setembro | D4: Compra de Shampoo | E4: Shampoo Antiqueda | F4: 12 | G4: 25 | H4: 300
B5: 2024-09-04 | C5: Setembro | D5: Compra de Condicionador | E5: Condicionador Nutritivo | F5: 10 | G5: 20 | H5: 200
B6: 2024-09-06 | C6: Setembro | D6: Compra de Ampola | E6: Ampola de Reparação | F6: 8 | G6: 15 | H6: 120
B7: 2024-09-09 | C7: Setembro | D7: Compra de Máscara | E7: Máscara de Hidratação | F7: 25 | G7: 10 | H7: 250
B8: 2024-09-11 | C8: Setembro | D8: Compra de Óleo | E8: Óleo de Rícino | F8: 12 | G8: 18 | H8: 216
B9: 2024-09-14 | C9: Setembro | D9: Compra de Creme de Pentear | E9: Creme de Pentear Hidratante | F9: 13 | G9: 15 | H9: 195
B10: 2024-09-19 | C10: Setembro | D10: Compra de Máscara | E10: Máscara de Nutrição Profunda | F10: 30 | G10: 10 | H10: 300
B11: 2024-09-21 | C11: Setembro | D11: Compra de Leave-in | E11: Leave-in Nutritivo | F11: 14 | G11: 15 | H11: 210
B12: 2024-09-24 | C12: Setembro | D12: Compra de Condicionador | E12: Condicionador Antifrizz | F12: 19 | G12: 8 | H12: 152
B13: 2024-10-01 | C13: Outubro | D13: Compra de Óleo | E13: Óleo de Rícino | F13: 12 | G13: 30 | H13: 360
B14: 2024-10-02 | C14: Outubro | D14: Compra de Creme de Pentear | E14: Creme de Pentear Antifrizz | F14: 10 | G14: 20 | H14: 200
B15: 2024-10-03 | C15: Outubro | D15: Compra de Creme de Pentear | E15: Creme de Pentear Hidratante | F15: 13 | G15: 10 | H15: 130
... B39: 2024-11-18 | C39: Novembro | D39: Compra de Óleo | E39: Óleo de Jojoba | F39: 17 | G39: 15 | H39: 255
H40: =IF(AND(F40<>"",G40<>""),F40*G40,0) -> 0
H41: =IF(AND(F41<>"",G41<>""),F41*G41,0) -> 0
H42: =IF(AND(F42<>"",G42<>""),F42*G42,0) -> 0
H43: =IF(AND(F43<>"",G43<>""),F43*G43,0) -> 0
H44: =IF(AND(F44<>"",G44<>""),F44*G44,0) -> 0
H45: =IF(AND(F45<>"",G45<>""),F45*G45,0) -> 0
H46: =IF(AND(F46<>"",G46<>""),F46*G46,0) -> 0
H47: =IF(AND(F47<>"",G47<>""),F47*G47,0) -> 0
H48: =IF(AND(F48<>"",G48<>""),F48*G48,0) -> 0
H49: =IF(AND(F49<>"",G49<>""),F49*G49,0) -> 0
H50: =IF(AND(F50<>"",G50<>""),F50*G50,0) -> 0
H51: =IF(AND(F51<>"",G51<>""),F51*G51,0) -> 0
... H99: =IF(AND(F99<>"",G99<>""),F99*G99,0) -> 0

Sheet Dados_Graficos
A1: Esta aba contém apenas fórmulas de apoio para os gráficos do Dashboard. Não editar.
A3: Mês | B3: Faturamento (R$) | D3: Produto (espelho) | E3: Score | G3: Produto | H3: Qtd
A4: Setembro | B4: =SUMIF(Pedidos_DB!$C$4:$C$110,A4,Pedidos_DB!$G$4:$G$110) -> 3550.9 | D4: =Estoque!C9 -> Shampoo Antiqueda | E4: =Estoque!F9*1000+(66-10) -> 30056 | G4: =INDEX($D$4:$D$60,MATCH(LARGE($E$4:$E$60,1),$E$4:$E$60,0)) -> Óleo de Argan | H4: =ROUNDDOWN(LARGE($E$4:$E$60,1)/1000,0) -> 77
A5: Outubro | B5: =SUMIF(Pedidos_DB!$C$4:$C$110,A5,Pedidos_DB!$G$4:$G$110) -> 8328.2 | D5: =Estoque!C10 -> Shampoo Detox | E5: =Estoque!F10*1000+(66-11) -> 35055 | G5: =INDEX($D$4:$D$60,MATCH(LARGE($E$4:$E$60,2),$E$4:$E$60,0)) -> Leave-in Hidratante | H5: =ROUNDDOWN(LARGE($E$4:$E$60,2)/1000,0) -> 75
A6: Novembro | B6: =SUMIF(Pedidos_DB!$C$4:$C$110,A6,Pedidos_DB!$G$4:$G$110) -> 6187.3 | D6: =Estoque!C11 -> Shampoo Antirresíduos | E6: =Estoque!F11*1000+(66-12) -> 45054 | G6: =INDEX($D$4:$D$60,MATCH(LARGE($E$4:$E$60,3),$E$4:$E$60,0)) -> Creme de Pentear Modelador de Cachos | H6: =ROUNDDOWN(LARGE($E$4:$E$60,3)/1000,0) -> 57
A7: Dezembro | B7: =SUMIF(Pedidos_DB!$C$4:$C$110,A7,Pedidos_DB!$G$4:$G$110) -> 0 | D7: =Estoque!C12 -> Shampoo Reparador | E7: =Estoque!F12*1000+(66-13) -> 32053 | G7: =INDEX($D$4:$D$60,MATCH(LARGE($E$4:$E$60,4),$E$4:$E$60,0)) -> Condicionador Nutritivo | H7: =ROUNDDOWN(LARGE($E$4:$E$60,4)/1000,0) -> 56
D8: =Estoque!C13 -> Shampoo Hidratante | E8: =Estoque!F13*1000+(66-14) -> 25052 | G8: =INDEX($D$4:$D$60,MATCH(LARGE($E$4:$E$60,5),$E$4:$E$60,0)) -> Máscara Hidratante de Coco | H8: =ROUNDDOWN(LARGE($E$4:$E$60,5)/1000,0) -> 55
D9: =Estoque!C14 -> Shampoo Revitalizante | E9: =Estoque!F14*1000+(66-15) -> 20051 | G9: =INDEX($D$4:$D$60,MATCH(LARGE($E$4:$E$60,6),$E$4:$E$60,0)) -> Ampola de Fortalecimento | H9: =ROUNDDOWN(LARGE($E$4:$E$60,6)/1000,0) -> 52
D10: =Estoque!C15 -> Shampoo Anti-frizz | E10: =Estoque!F15*1000+(66-16) -> 15050 | G10: =INDEX($D$4:$D$60,MATCH(LARGE($E$4:$E$60,7),$E$4:$E$60,0)) -> Óleo de Rícino | H10: =ROUNDDOWN(LARGE($E$4:$E$60,7)/1000,0) -> 50
D11: =Estoque!C16 -> Shampoo para Cabelos Cacheados | E11: =Estoque!F16*1000+(66-17) -> 20049 | G11: =INDEX($D$4:$D$60,MATCH(LARGE($E$4:$E$60,8),$E$4:$E$60,0)) -> Leave-in para Cabelos Cacheados | H11: =ROUNDDOWN(LARGE($E$4:$E$60,8)/1000,0) -> 50
D12: =Estoque!C17 -> Condicionador Nutritivo | E12: =Estoque!F17*1000+(66-18) -> 56048 | G12: =INDEX($D$4:$D$60,MATCH(LARGE($E$4:$E$60,9),$E$4:$E$60,0)) -> Shampoo Antirresíduos | H12: =ROUNDDOWN(LARGE($E$4:$E$60,9)/1000,0) -> 45
D13: =Estoque!C18 -> Condicionador Revitalizante | E13: =Estoque!F18*1000+(66-19) -> 35047 | G13: =INDEX($D$4:$D$60,MATCH(LARGE($E$4:$E$60,10),$E$4:$E$60,0)) -> Ampola de Reparação | H13: =ROUNDDOWN(LARGE($E$4:$E$60,10)/1000,0) -> 45
D14: =Estoque!C19 -> Condicionador Hidratante | E14: =Estoque!F19*1000+(66-20) -> 28046 | G14: =INDEX($D$4:$D$60,MATCH(LARGE($E$4:$E$60,11),$E$4:$E$60,0)) -> Leave-in Nutritivo | H14: =ROUNDDOWN(LARGE($E$4:$E$60,11)/1000,0) -> 40
D15: =Estoque!C20 -> Condicionador Antifrizz | E15: =Estoque!F20*1000+(66-21) -> 20045 | G15: =INDEX($D$4:$D$60,MATCH(LARGE($E$4:$E$60,12),$E$4:$E$60,0)) -> Creme de Pentear Antifrizz | H15: =ROUNDDOWN(LARGE($E$4:$E$60,12)/1000,0) -> 40
D16: =Estoque!C21 -> Condicionador Reestruturante | E16: =Estoque!F21*1000+(66-22) -> 15044
D17: =Estoque!C22 -> Condicionador de Cabelos Cacheados | E17: =Estoque!F22*1000+(66-23) -> 15043
D18: =Estoque!C23 -> Condicionador Reconstrutor | E18: =Estoque!F23*1000+(66-24) -> 20042
D19: =Estoque!C24 -> Ampola de Reparação | E19: =Estoque!F24*1000+(66-25) -> 45041
D20: =Estoque!C25 -> Ampola de Reconstrução | E20: =Estoque!F25*1000+(66-26) -> 30040
D21: =Estoque!C26 -> Ampola de Fortalecimento | E21: =Estoque!F26*1000+(66-27) -> 52039
D22: =Estoque!C27 -> Ampola de Brilho | E22: =Estoque!F27*1000+(66-28) -> 30038
D23: =Estoque!C28 -> Ampola de Hidratação Intensiva | E23: =Estoque!F28*1000+(66-29) -> 25037
D24: =Estoque!C29 -> Ampola de Hidratação de Óleo de Argan | E24: =Estoque!F29*1000+(66-30) -> 15036
D25: =Estoque!C30 -> Ampola de Reconstrução Capilar | E25: =Estoque!F30*1000+(66-31) -> 20035
D26: =Estoque!C31 -> Ampola de Reparação Intensiva | E26: =Estoque!F31*1000+(66-32) -> 20034
D27: =Estoque!C32 -> Ampola de Reparação Capilar | E27: =Estoque!F32*1000+(66-33) -> 10033
D28: =Estoque!C33 -> Ampola de Fortalecimento Capilar | E28: =Estoque!F33*1000+(66-34) -> 15032
D29: =Estoque!C34 -> Ampola Anticabelos | E29: =Estoque!F34*1000+(66-35) -> 10031
D30: =Estoque!C35 -> Máscara de Hidratação | E30: =Estoque!F35*1000+(66-36) -> 15030
D31: =Estoque!C36 -> Máscara Reconstrutora | E31: =Estoque!F36*1000+(66-37) -> 8029
D32: =Estoque!C37 -> Máscara Reparadora de Pontas | E32: =Estoque!F37*1000+(66-38) -> 35028
D33: =Estoque!C38 -> Máscara de Nutrição Profunda | E33: =Estoque!F38*1000+(66-39) -> 15027
D34: =Estoque!C39 -> Máscara de Reconstrução | E34: =Estoque!F39*1000+(66-40) -> 20026
D35: =Estoque!C40 -> Máscara Hidratante de Coco | E35: =Estoque!F40*1000+(66-41) -> 55025
D36: =Estoque!C41 -> Máscara de Hidratação Intensa | E36: =Estoque!F41*1000+(66-42) -> 35024
D37: =Estoque!C42 -> Máscara de Reconstrução Capilar | E37: =Estoque!F42*1000+(66-43) -> 15023
D38: =Estoque!C43 -> Máscara Nutritiva | E38: =Estoque!F43*1000+(66-44) -> 20022
D39: =Estoque!C44 -> Óleo de Argan | E39: =Estoque!F44*1000+(66-45) -> 77021
D40: =Estoque!C45 -> Óleo de Rícino | E40: =Estoque!F45*1000+(66-46) -> 50020
D41: =Estoque!C46 -> Óleo de Jojoba | E41: =Estoque!F46*1000+(66-47) -> 30019
D42: =Estoque!C47 -> Óleo de Abacate | E42: =Estoque!F47*1000+(66-48) -> 30018
D43: =Estoque!C48 -> Óleo de Macadâmia | E43: =Estoque!F48*1000+(66-49) -> 20017
D44: =Estoque!C49 -> Óleo de Amêndoas | E44: =Estoque!F49*1000+(66-50) -> 15016
D45: =Estoque!C50 -> Óleo Essencial de Lavanda | E45: =Estoque!F50*1000+(66-51) -> 20015
D46: =Estoque!C51 -> Leave-in Nutritivo | E46: =Estoque!F51*1000+(66-52) -> 40014
D47: =Estoque!C52 -> Leave-in para Cabelos Cacheados | E47: =Estoque!F52*1000+(66-53) -> 50013
D48: =Estoque!C53 -> Leave-in Hidratante | E48: =Estoque!F53*1000+(66-54) -> 75012
D49: =Estoque!C54 -> Leave-in Reparador | E49: =Estoque!F54*1000+(66-55) -> 25011
D50: =Estoque!C55 -> Leave-in Antifriz | E50: =Estoque!F55*1000+(66-56) -> 25010
D51: =Estoque!C56 -> Leave-in Com Proteção Térmica | E51: =Estoque!F56*1000+(66-57) -> 20009
D52: =Estoque!C57 -> Leave-in Com Proteção UV | E52: =Estoque!F57*1000+(66-58) -> 20008
D53: =Estoque!C58 -> Leave-in Defrizante | E53: =Estoque!F58*1000+(66-59) -> 20007
D54: =Estoque!C59 -> Creme de Pentear Antifrizz | E54: =Estoque!F59*1000+(66-60) -> 40006
D55: =Estoque!C60 -> Creme de Pentear Hidratante | E55: =Estoque!F60*1000+(66-61) -> 35005
D56: =Estoque!C61 -> Creme de Pentear Modelador de Cachos | E56: =Estoque!F61*1000+(66-62) -> 57004
D57: =Estoque!C62 -> Creme de Pentear Reparador | E57: =Estoque!F62*1000+(66-63) -> 30003
D58: =Estoque!C63 -> Creme de Pentear Cabelos Cacheados | E58: =Estoque!F63*1000+(66-64) -> 25002
D59: =Estoque!C64 -> Creme de Pentear Defrizante | E59: =Estoque!F64*1000+(66-65) -> 20001
D60: =Estoque!C65 -> Creme de Pentear Anti-frizz | E60: =Estoque!F65*1000+(66-66) -> 20000
B65: 🏆 Top Produtos por Faturamento
B66: Produto | G66: Faturamento | I66: Custo | K66: Lucro | M66: Margem | N66: Qtd
B67: Shampoo Antiqueda | G67: =SUMPRODUCT((Pedidos_DB!C4:C110=Dashboard!$E$3)*(Pedidos_DB!E4:E110=B67)*Pedidos_DB!G4:G110) -> 283.5 | I67: =SUMIFS(Despesas_DB!H4:H99,Despesas_DB!C4:C99,Dashboard!$E$3,Despesas_DB!E4:E99,B67) -> 300 | K67: =G67-I67 -> -16.5 | M67: =IFERROR(K67/G67,0) -> -0.058201058 | N67: =SUMPRODUCT((Pedidos_DB!C4:C110=Dashboard!$E$3)*(Pedidos_DB!E4:E110=B67)*Pedidos_DB!F4:F110) -> 15
B68: Condicionador Nutritivo | G68: =SUMPRODUCT((Pedidos_DB!C4:C110=Dashboard!$E$3)*(Pedidos_DB!E4:E110=B68)*Pedidos_DB!G4:G110) -> 356 | I68: =SUMIFS(Despesas_DB!H4:H99,Despesas_DB!C4:C99,Dashboard!$E$3,Despesas_DB!E4:E99,B68) -> 200 | K68: =G68-I68 -> 156 | M68: =IFERROR(K68/G68,0) -> 0.43820225 | N68: =SUMPRODUCT((Pedidos_DB!C4:C110=Dashboard!$E$3)*(Pedidos_DB!E4:E110=B68)*Pedidos_DB!F4:F110) -> 20
B69: Ampola de Reparação | G69: =SUMPRODUCT((Pedidos_DB!C4:C110=Dashboard!$E$3)*(Pedidos_DB!E4:E110=B69)*Pedidos_DB!G4:G110) -> 125 | I69: =SUMIFS(Despesas_DB!H4:H99,Despesas_DB!C4:C99,Dashboard!$E$3,Despesas_DB!E4:E99,B69) -> 120 | K69: =G69-I69 -> 5 | M69: =IFERROR(K69/G69,0) -> 0.04 | N69: =SUMPRODUCT((Pedidos_DB!C4:C110=Dashboard!$E$3)*(Pedidos_DB!E4:E110=B69)*Pedidos_DB!F4:F110) -> 10
B70: Máscara de Hidratação | G70: =SUMPRODUCT((Pedidos_DB!C4:C110=Dashboard!$E$3)*(Pedidos_DB!E4:E110=B70)*Pedidos_DB!G4:G110) -> 420 | I70: =SUMIFS(Despesas_DB!H4:H99,Despesas_DB!C4:C99,Dashboard!$E$3,Despesas_DB!E4:E99,B70) -> 250 | K70: =G70-I70 -> 170 | M70: =IFERROR(K70/G70,0) -> 0.4047619 | N70: =SUMPRODUCT((Pedidos_DB!C4:C110=Dashboard!$E$3)*(Pedidos_DB!E4:E110=B70)*Pedidos_DB!F4:F110) -> 12
B71: Óleo de Rícino | G71: =SUMPRODUCT((Pedidos_DB!C4:C110=Dashboard!$E$3)*(Pedidos_DB!E4:E110=B71)*Pedidos_DB!G4:G110) -> 360 | I71: =SUMIFS(Despesas_DB!H4:H99,Despesas_DB!C4:C99,Dashboard!$E$3,Despesas_DB!E4:E99,B71) -> 216 | K71: =G71-I71 -> 144 | M71: =IFERROR(K71/G71,0) -> 0.4 | N71: =SUMPRODUCT((Pedidos_DB!C4:C110=Dashboard!$E$3)*(Pedidos_DB!E4:E110=B71)*Pedidos_DB!F4:F110) -> 18
B72: Creme de Pentear Hidratante | G72: =SUMPRODUCT((Pedidos_DB!C4:C110=Dashboard!$E$3)*(Pedidos_DB!E4:E110=B72)*Pedidos_DB!G4:G110) -> 273 | I72: =SUMIFS(Despesas_DB!H4:H99,Despesas_DB!C4:C99,Dashboard!$E$3,Despesas_DB!E4:E99,B72) -> 195 | K72: =G72-I72 -> 78 | M72: =IFERROR(K72/G72,0) -> 0.28571429 | N72: =SUMPRODUCT((Pedidos_DB!C4:C110=Dashboard!$E$3)*(Pedidos_DB!E4:E110=B72)*Pedidos_DB!F4:F110) -> 15
B73: Shampoo Detox | G73: =SUMPRODUCT((Pedidos_DB!C4:C110=Dashboard!$E$3)*(Pedidos_DB!E4:E110=B73)*Pedidos_DB!G4:G110) -> 398 | I73: =SUMIFS(Despesas_DB!H4:H99,Despesas_DB!C4:C99,Dashboard!$E$3,Despesas_DB!E4:E99,B73) -> 0 | K73: =G73-I73 -> 398 | M73: =IFERROR(K73/G73,0) -> 1 | N73: =SUMPRODUCT((Pedidos_DB!C4:C110=Dashboard!$E$3)*(Pedidos_DB!E4:E110=B73)*Pedidos_DB!F4:F110) -> 20
B74: Máscara de Nutrição Profunda | G74: =SUMPRODUCT((Pedidos_DB!C4:C110=Dashboard!$E$3)*(Pedidos_DB!E4:E110=B74)*Pedidos_DB!G4:G110) -> 420 | I74: =SUMIFS(Despesas_DB!H4:H99,Despesas_DB!C4:C99,Dashboard!$E$3,Despesas_DB!E4:E99,B74) -> 300 | K74: =G74-I74 -> 120 | M74: =IFERROR(K74/G74,0) -> 0.28571429 | N74: =SUMPRODUCT((Pedidos_DB!C4:C110=Dashboard!$E$3)*(Pedidos_DB!E4:E110=B74)*Pedidos_DB!F4:F110) -> 10
B75: Leave-in Nutritivo | G75: =SUMPRODUCT((Pedidos_DB!C4:C110=Dashboard!$E$3)*(Pedidos_DB!E4:E110=B75)*Pedidos_DB!G4:G110) -> 351 | I75: =SUMIFS(Despesas_DB!H4:H99,Despesas_DB!C4:C99,Dashboard!$E$3,Despesas_DB!E4:E99,B75) -> 210 | K75: =G75-I75 -> 141 | M75: =IFERROR(K75/G75,0) -> 0.4017094 | N75: =SUMPRODUCT((Pedidos_DB!C4:C110=Dashboard!$E$3)*(Pedidos_DB!E4:E110=B75)*Pedidos_DB!F4:F110) -> 15
B78: 🏪 Faturamento por Salão | H78: 📋 Status dos Pedidos
B79: Salão | F79: Faturamento (R$) | H79: Status | K79: Qtd | L79: Ticket Médio | N79: %
B80: Salão Beleza & Cia | F80: =SUMPRODUCT((Pedidos_DB!C4:C110=Dashboard!$E$3)*(Pedidos_DB!D4:D110=B80)*Pedidos_DB!G4:G110) -> 545 | H80: ✅ Concluídos | K80: =SUMPRODUCT((Pedidos_DB!C4:C110=Dashboard!$E$3)*(LOWER(Pedidos_DB!H4:H110)="concluído")) -> 11 | L80: =IFERROR(SUMPRODUCT((Pedidos_DB!C4:C110=Dashboard!$E$3)*(LOWER(Pedidos_DB!H4:H110)="concluído")*Pedidos_DB!G4:G110)/K80,0) -> 322.80909 | N80: =IFERROR(K80/Dashboard!D10,0) -> 1
B81: Salão Glamour | F81: =SUMPRODUCT((Pedidos_DB!C4:C110=Dashboard!$E$3)*(Pedidos_DB!D4:D110=B81)*Pedidos_DB!G4:G110) -> 795.7 | H81: ⏳ Pendentes | K81: =SUMPRODUCT((Pedidos_DB!C4:C110=Dashboard!$E$3)*(LOWER(Pedidos_DB!H4:H110)="pendente")) -> 0 | L81: =IFERROR(SUMPRODUCT((Pedidos_DB!C4:C110=Dashboard!$E$3)*(LOWER(Pedidos_DB!H4:H110)="pendente")*Pedidos_DB!G4:G110)/K81,0) -> 0 | N81: =IFERROR(K81/Dashboard!D10,0) -> 0
B82: Salão Luxo Capilar | F82: =SUMPRODUCT((Pedidos_DB!C4:C110=Dashboard!$E$3)*(Pedidos_DB!D4:D110=B82)*Pedidos_DB!G4:G110) -> 685.2 | H82: 🔄 Processo | K82: =SUMPRODUCT((Pedidos_DB!C4:C110=Dashboard!$E$3)*(LOWER(Pedidos_DB!H4:H110)="processo")) -> 0 | L82: =IFERROR(SUMPRODUCT((Pedidos_DB!C4:C110=Dashboard!$E$3)*(LOWER(Pedidos_DB!H4:H110)="processo")*Pedidos_DB!G4:G110)/K82,0) -> 0 | N82: =IFERROR(K82/Dashboard!D10,0) -> 0
B83: Salão Cabelos de Ouro | F83: =SUMPRODUCT((Pedidos_DB!C4:C110=Dashboard!$E$3)*(Pedidos_DB!D4:D110=B83)*Pedidos_DB!G4:G110) -> 754
B84: Salão Bella Cabelos | F84: =SUMPRODUCT((Pedidos_DB!C4:C110=Dashboard!$E$3)*(Pedidos_DB!D4:D110=B84)*Pedidos_DB!G4:G110) -> 771
